Workbook

Sheet Dashboard
A1: RETAIL SALES PERFORMANCE DASHBOARD
A4: Total Net Revenue | E4: Total Profit | I4: Completed Orders
A5: =SUMIFS(Clean_Data!R2:R301,Clean_Data!V2:V301,"VALID",Clean_Data!P2:P301,"Completed") -> 661760.25 | E5: =SUMIFS(Clean_Data!T2:T301,Clean_Data!V2:V301,"VALID",Clean_Data!P2:P301,"Completed") -> 170908.25 | I5: =COUNTIFS(Clean_Data!V2:V301,"VALID",Clean_Data!P2:P301,"Completed") -> 204
A8: Average Order Value | E8: Profit Margin | I8: Data Quality Score
A9: =IFERROR(A5/I5,0) -> 3243.9228 | E9: =IFERROR(E5/A5,0) -> 0.25826309 | I9: =Data_Validation!B7 -> 0.97
A13: Month | B13: Net Revenue | C13: Profit | D13: Completed Orders | F13: Region | G13: Net Revenue | H13: Profit | I13: Orders
A14: 45658 | B14: =SUMIFS(Clean_Data!$R$2:$R$301,Clean_Data!$B$2:$B$301,">="&A14,Clean_Data!$B$2:$B$301,"<"&EDATE(A14,1),Clean_Data!$V$2:$V$301,"VALID",Clean_Data!$P$2:$P$301,"Completed") -> 47265.25 | C14: =SUMIFS(Clean_Data!$T$2:$T$301,Clean_Data!$B$2:$B$301,">="&A14,Clean_Data!$B$2:$B$301,"<"&EDATE(A14,1),Clean_Data!$V$2:$V$301,"VALID",Clean_Data!$P$2:$P$301,"Completed") -> 12056.25 | D14: =COUNTIFS(Clean_Data!$B$2:$B$301,">="&A14,Clean_Data!$B$2:$B$301,"<"&EDATE(A14,1),Clean_Data!$V$2:$V$301,"VALID",Clean_Data!$P$2:$P$301,"Completed") -> 16 | F14: Bucharest | G14: =SUMIFS(Clean_Data!$R$2:$R$301,Clean_Data!$H$2:$H$301,F14,Clean_Data!$V$2:$V$301,"VALID",Clean_Data!$P$2:$P$301,"Completed") -> 84871 | H14: =SUMIFS(Clean_Data!$T$2:$T$301,Clean_Data!$H$2:$H$301,F14,Clean_Data!$V$2:$V$301,"VALID",Clean_Data!$P$2:$P$301,"Completed") -> 22597 | I14: =COUNTIFS(Clean_Data!$H$2:$H$301,F14,Clean_Data!$V$2:$V$301,"VALID",Clean_Data!$P$2:$P$301,"Completed") -> 36
A15: 45689 | B15: =SUMIFS(Clean_Data!$R$2:$R$301,Clean_Data!$B$2:$B$301,">="&A15,Clean_Data!$B$2:$B$301,"<"&EDATE(A15,1),Clean_Data!$V$2:$V$301,"VALID",Clean_Data!$P$2:$P$301,"Completed") -> 43138.25 | C15: =SUMIFS(Clean_Data!$T$2:$T$301,Clean_Data!$B$2:$B$301,">="&A15,Clean_Data!$B$2:$B$301,"<"&EDATE(A15,1),Clean_Data!$V$2:$V$301,"VALID",Clean_Data!$P$2:$P$301,"Completed") -> 11242.25 | D15: =COUNTIFS(Clean_Data!$B$2:$B$301,">="&A15,Clean_Data!$B$2:$B$301,"<"&EDATE(A15,1),Clean_Data!$V$2:$V$301,"VALID",Clean_Data!$P$2:$P$301,"Completed") -> 12 | F15: North | G15: =SUMIFS(Clean_Data!$R$2:$R$301,Clean_Data!$H$2:$H$301,F15,Clean_Data!$V$2:$V$301,"VALID",Clean_Data!$P$2:$P$301,"Completed") -> 121630.25 | H15: =SUMIFS(Clean_Data!$T$2:$T$301,Clean_Data!$H$2:$H$301,F15,Clean_Data!$V$2:$V$301,"VALID",Clean_Data!$P$2:$P$301,"Completed") -> 32267.25 | I15: =COUNTIFS(Clean_Data!$H$2:$H$301,F15,Clean_Data!$V$2:$V$301,"VALID",Clean_Data!$P$2:$P$301,"Completed") -> 36
A16: 45717 | B16: =SUMIFS(Clean_Data!$R$2:$R$301,Clean_Data!$B$2:$B$301,">="&A16,Clean_Data!$B$2:$B$301,"<"&EDATE(A16,1),Clean_Data!$V$2:$V$301,"VALID",Clean_Data!$P$2:$P$301,"Completed") -> 31816 | C16: =SUMIFS(Clean_Data!$T$2:$T$301,Clean_Data!$B$2:$B$301,">="&A16,Clean_Data!$B$2:$B$301,"<"&EDATE(A16,1),Clean_Data!$V$2:$V$301,"VALID",Clean_Data!$P$2:$P$301,"Completed") -> 9222 | D16: =COUNTIFS(Clean_Data!$B$2:$B$301,">="&A16,Clean_Data!$B$2:$B$301,"<"&EDATE(A16,1),Clean_Data!$V$2:$V$301,"VALID",Clean_Data!$P$2:$P$301,"Completed") -> 13 | F16: South | G16: =SUMIFS(Clean_Data!$R$2:$R$301,Clean_Data!$H$2:$H$301,F16,Clean_Data!$V$2:$V$301,"VALID",Clean_Data!$P$2:$P$301,"Completed") -> 194550.75 | H16: =SUMIFS(Clean_Data!$T$2:$T$301,Clean_Data!$H$2:$H$301,F16,Clean_Data!$V$2:$V$301,"VALID",Clean_Data!$P$2:$P$301,"Completed") -> 49004.75 | I16: =COUNTIFS(Clean_Data!$H$2:$H$301,F16,Clean_Data!$V$2:$V$301,"VALID",Clean_Data!$P$2:$P$301,"Completed") -> 46
A17: 45748 | B17: =SUMIFS(Clean_Data!$R$2:$R$301,Clean_Data!$B$2:$B$301,">="&A17,Clean_Data!$B$2:$B$301,"<"&EDATE(A17,1),Clean_Data!$V$2:$V$301,"VALID",Clean_Data!$P$2:$P$301,"Completed") -> 61868.75 | C17: =SUMIFS(Clean_Data!$T$2:$T$301,Clean_Data!$B$2:$B$301,">="&A17,Clean_Data!$B$2:$B$301,"<"&EDATE(A17,1),Clean_Data!$V$2:$V$301,"VALID",Clean_Data!$P$2:$P$301,"Completed") -> 15412.75 | D17: =COUNTIFS(Clean_Data!$B$2:$B$301,">="&A17,Clean_Data!$B$2:$B$301,"<"&EDATE(A17,1),Clean_Data!$V$2:$V$301,"VALID",Clean_Data!$P$2:$P$301,"Completed") -> 13 | F17: East | G17: =SUMIFS(Clean_Data!$R$2:$R$301,Clean_Data!$H$2:$H$301,F17,Clean_Data!$V$2:$V$301,"VALID",Clean_Data!$P$2:$P$301,"Completed") -> 147815.75 | H17: =SUMIFS(Clean_Data!$T$2:$T$301,Clean_Data!$H$2:$H$301,F17,Clean_Data!$V$2:$V$301,"VALID",Clean_Data!$P$2:$P$301,"Completed") -> 36950.75 | I17: =COUNTIFS(Clean_Data!$H$2:$H$301,F17,Clean_Data!$V$2:$V$301,"VALID",Clean_Data!$P$2:$P$301,"Completed") -> 41
A18: 45778 | B18: =SUMIFS(Clean_Data!$R$2:$R$301,Clean_Data!$B$2:$B$301,">="&A18,Clean_Data!$B$2:$B$301,"<"&EDATE(A18,1),Clean_Data!$V$2:$V$301,"VALID",Clean_Data!$P$2:$P$301,"Completed") -> 52849.75 | C18: =SUMIFS(Clean_Data!$T$2:$T$301,Clean_Data!$B$2:$B$301,">="&A18,Clean_Data!$B$2:$B$301,"<"&EDATE(A18,1),Clean_Data!$V$2:$V$301,"VALID",Clean_Data!$P$2:$P$301,"Completed") -> 14995.75 | D18: =COUNTIFS(Clean_Data!$B$2:$B$301,">="&A18,Clean_Data!$B$2:$B$301,"<"&EDATE(A18,1),Clean_Data!$V$2:$V$301,"VALID",Clean_Data!$P$2:$P$301,"Completed") -> 15 | F18: West | G18: =SUMIFS(Clean_Data!$R$2:$R$301,Clean_Data!$H$2:$H$301,F18,Clean_Data!$V$2:$V$301,"VALID",Clean_Data!$P$2:$P$301,"Completed") -> 112892.5 | H18: =SUMIFS(Clean_Data!$T$2:$T$301,Clean_Data!$H$2:$H$301,F18,Clean_Data!$V$2:$V$301,"VALID",Clean_Data!$P$2:$P$301,"Completed") -> 30088.5 | I18: =COUNTIFS(Clean_Data!$H$2:$H$301,F18,Clean_Data!$V$2:$V$301,"VALID",Clean_Data!$P$2:$P$301,"Completed") -> 45
A19: 45809 | B19: =SUMIFS(Clean_Data!$R$2:$R$301,Clean_Data!$B$2:$B$301,">="&A19,Clean_Data!$B$2:$B$301,"<"&EDATE(A19,1),Clean_Data!$V$2:$V$301,"VALID",Clean_Data!$P$2:$P$301,"Completed") -> 57249.25 | C19: =SUMIFS(Clean_Data!$T$2:$T$301,Clean_Data!$B$2:$B$301,">="&A19,Clean_Data!$B$2:$B$301,"<"&EDATE(A19,1),Clean_Data!$V$2:$V$301,"VALID",Clean_Data!$P$2:$P$301,"Completed") -> 16863.25 | D19: =COUNTIFS(Clean_Data!$B$2:$B$301,">="&A19,Clean_Data!$B$2:$B$301,"<"&EDATE(A19,1),Clean_Data!$V$2:$V$301,"VALID",Clean_Data!$P$2:$P$301,"Completed") -> 23
A20: 45839 | B20: =SUMIFS(Clean_Data!$R$2:$R$301,Clean_Data!$B$2:$B$301,">="&A20,Clean_Data!$B$2:$B$301,"<"&EDATE(A20,1),Clean_Data!$V$2:$V$301,"VALID",Clean_Data!$P$2:$P$301,"Completed") -> 29954.75 | C20: =SUMIFS(Clean_Data!$T$2:$T$301,Clean_Data!$B$2:$B$301,">="&A20,Clean_Data!$B$2:$B$301,"<"&EDATE(A20,1),Clean_Data!$V$2:$V$301,"VALID",Clean_Data!$P$2:$P$301,"Completed") -> 6969.75 | D20: =COUNTIFS(Clean_Data!$B$2:$B$301,">="&A20,Clean_Data!$B$2:$B$301,"<"&EDATE(A20,1),Clean_Data!$V$2:$V$301,"VALID",Clean_Data!$P$2:$P$301,"Completed") -> 14
A21: 45870 | B21: =SUMIFS(Clean_Data!$R$2:$R$301,Clean_Data!$B$2:$B$301,">="&A21,Clean_Data!$B$2:$B$301,"<"&EDATE(A21,1),Clean_Data!$V$2:$V$301,"VALID",Clean_Data!$P$2:$P$301,"Completed") -> 63109.5 | C21: =SUMIFS(Clean_Data!$T$2:$T$301,Clean_Data!$B$2:$B$301,">="&A21,Clean_Data!$B$2:$B$301,"<"&EDATE(A21,1),Clean_Data!$V$2:$V$301,"VALID",Clean_Data!$P$2:$P$301,"Completed") -> 18403.5 | D21: =COUNTIFS(Clean_Data!$B$2:$B$301,">="&A21,Clean_Data!$B$2:$B$301,"<"&EDATE(A21,1),Clean_Data!$V$2:$V$301,"VALID",Clean_Data!$P$2:$P$301,"Completed") -> 25 | F21: Category | G21: Net Revenue | H21: Profit | I21: Margin
A22: 45901 | B22: =SUMIFS(Clean_Data!$R$2:$R$301,Clean_Data!$B$2:$B$301,">="&A22,Clean_Data!$B$2:$B$301,"<"&EDATE(A22,1),Clean_Data!$V$2:$V$301,"VALID",Clean_Data!$P$2:$P$301,"Completed") -> 73064.25 | C22: =SUMIFS(Clean_Data!$T$2:$T$301,Clean_Data!$B$2:$B$301,">="&A22,Clean_Data!$B$2:$B$301,"<"&EDATE(A22,1),Clean_Data!$V$2:$V$301,"VALID",Clean_Data!$P$2:$P$301,"Completed") -> 19409.25 | D22: =COUNTIFS(Clean_Data!$B$2:$B$301,">="&A22,Clean_Data!$B$2:$B$301,"<"&EDATE(A22,1),Clean_Data!$V$2:$V$301,"VALID",Clean_Data!$P$2:$P$301,"Completed") -> 17 | F22: Accessories | G22: =SUMIFS(Clean_Data!$R$2:$R$301,Clean_Data!$G$2:$G$301,F22,Clean_Data!$V$2:$V$301,"VALID",Clean_Data!$P$2:$P$301,"Completed") -> 66527 | H22: =SUMIFS(Clean_Data!$T$2:$T$301,Clean_Data!$G$2:$G$301,F22,Clean_Data!$V$2:$V$301,"VALID",Clean_Data!$P$2:$P$301,"Completed") -> 25449 | I22: =IFERROR(H22/G22,0) -> 0.38253641
A23: 45931 | B23: =SUMIFS(Clean_Data!$R$2:$R$301,Clean_Data!$B$2:$B$301,">="&A23,Clean_Data!$B$2:$B$301,"<"&EDATE(A23,1),Clean_Data!$V$2:$V$301,"VALID",Clean_Data!$P$2:$P$301,"Completed") -> 46952.25 | C23: =SUMIFS(Clean_Data!$T$2:$T$301,Clean_Data!$B$2:$B$301,">="&A23,Clean_Data!$B$2:$B$301,"<"&EDATE(A23,1),Clean_Data!$V$2:$V$301,"VALID",Clean_Data!$P$2:$P$301,"Completed") -> 10678.25 | D23: =COUNTIFS(Clean_Data!$B$2:$B$301,">="&A23,Clean_Data!$B$2:$B$301,"<"&EDATE(A23,1),Clean_Data!$V$2:$V$301,"VALID",Clean_Data!$P$2:$P$301,"Completed") -> 16 | F23: Electronics | G23: =SUMIFS(Clean_Data!$R$2:$R$301,Clean_Data!$G$2:$G$301,F23,Clean_Data!$V$2:$V$301,"VALID",Clean_Data!$P$2:$P$301,"Completed") -> 257639.75 | H23: =SUMIFS(Clean_Data!$T$2:$T$301,Clean_Data!$G$2:$G$301,F23,Clean_Data!$V$2:$V$301,"VALID",Clean_Data!$P$2:$P$301,"Completed") -> 67695.75 | I23: =IFERROR(H23/G23,0) -> 0.26275352
A24: 45962 | B24: =SUMIFS(Clean_Data!$R$2:$R$301,Clean_Data!$B$2:$B$301,">="&A24,Clean_Data!$B$2:$B$301,"<"&EDATE(A24,1),Clean_Data!$V$2:$V$301,"VALID",Clean_Data!$P$2:$P$301,"Completed") -> 90837.75 | C24: =SUMIFS(Clean_Data!$T$2:$T$301,Clean_Data!$B$2:$B$301,">="&A24,Clean_Data!$B$2:$B$301,"<"&EDATE(A24,1),Clean_Data!$V$2:$V$301,"VALID",Clean_Data!$P$2:$P$301,"Completed") -> 20538.75 | D24: =COUNTIFS(Clean_Data!$B$2:$B$301,">="&A24,Clean_Data!$B$2:$B$301,"<"&EDATE(A24,1),Clean_Data!$V$2:$V$301,"VALID",Clean_Data!$P$2:$P$301,"Completed") -> 17 | F24: Furniture | G24: =SUMIFS(Clean_Data!$R$2:$R$301,Clean_Data!$G$2:$G$301,F24,Clean_Data!$V$2:$V$301,"VALID",Clean_Data!$P$2:$P$301,"Completed") -> 337593.5 | H24: =SUMIFS(Clean_Data!$T$2:$T$301,Clean_Data!$G$2:$G$301,F24,Clean_Data!$V$2:$V$301,"VALID",Clean_Data!$P$2:$P$301,"Completed") -> 77763.5 | I24: =IFERROR(H24/G24,0) -> 0.23034656
A25: 45992 | B25: =SUMIFS(Clean_Data!$R$2:$R$301,Clean_Data!$B$2:$B$301,">="&A25,Clean_Data!$B$2:$B$301,"<"&EDATE(A25,1),Clean_Data!$V$2:$V$301,"VALID",Clean_Data!$P$2:$P$301,"Completed") -> 63654.5 | C25: =SUMIFS(Clean_Data!$T$2:$T$301,Clean_Data!$B$2:$B$301,">="&A25,Clean_Data!$B$2:$B$301,"<"&EDATE(A25,1),Clean_Data!$V$2:$V$301,"VALID",Clean_Data!$P$2:$P$301,"Completed") -> 15116.5 | D25: =COUNTIFS(Clean_Data!$B$2:$B$301,">="&A25,Clean_Data!$B$2:$B$301,"<"&EDATE(A25,1),Clean_Data!$V$2:$V$301,"VALID",Clean_Data!$P$2:$P$301,"Completed") -> 23
A47: Units Sold | E47: Average Discount | I47: Return Rate
A48: =SUMIFS(Clean_Data!K2:K301,Clean_Data!V2:V301,"VALID",Clean_Data!P2:P301,"Completed") -> 1322 | E48: =IFERROR(SUMIFS(Clean_Data!N2:N301,Clean_Data!V2:V301,"VALID",Clean_Data!P2:P301,"Completed")/COUNTIFS(Clean_Data!V2:V301,"VALID",Clean_Data!P2:P301,"Completed"),0) -> 0.080392157 | I48: =IFERROR(COUNTIFS(Clean_Data!V2:V301,"VALID",Clean_Data!P2:P301,"Returned")/COUNTIF(Clean_Data!V2:V301,"VALID"),0) -> 0.15120275
A51: Cancellation Rate | E51: Revenue / Customer | I51: Profit / Order
A52: =IFERROR(COUNTIFS(Clean_Data!V2:V301,"VALID",Clean_Data!P2:P301,"Cancelled")/COUNTIF(Clean_Data!V2:V301,"VALID"),0) -> 0.14776632 | E52: =IFERROR(SUMIFS(Clean_Data!R2:R301,Clean_Data!V2:V301,"VALID",Clean_Data!P2:P301,"Completed")/SUMPRODUCT((Clean_Data!V2:V301="VALID")*(Clean_Data!P2:P301="Completed")/COUNTIFS(Clean_Data!C2:C301,Clean_Data!C2:C301,Clean_Data!V2:V301,"VALID",Clean_Data!P2:P301,"Completed")),0) -> 0 | I52: =IFERROR(SUMIFS(Clean_Data!T2:T301,Clean_Data!V2:V301,"VALID",Clean_Data!P2:P301,"Completed")/COUNTIFS(Clean_Data!V2:V301,"VALID",Clean_Data!P2:P301,"Completed"),0) -> 837.78554

Sheet Filtered_Dashboard
A1: FILTERED SALES DASHBOARD
A4: Filter | B4: Selection | D4: Filter | E4: Selection
A5: Region | B5: All | D5: Category | E5: All
A6: Channel | B6: All | D6: Order Status | E6: Completed
A9: Filtered Revenue | C9: Filtered Profit | E9: Filtered Orders | G9: Units Sold | I9: Average Order Value | K9: Average Discount
A10: =SUMPRODUCT(((Clean_Data!H2:H301=$B$5)+($B$5="All"))*((Clean_Data!G2:G301=$E$5)+($E$5="All"))*((Clean_Data!I2:I301=$B$6)+($B$6="All"))*((Clean_Data!P2:P301=$E$6)+($E$6="All"))*(Clean_Data!AH2:AH301="READY FOR REPORTING")*Clean_Data!R2:R301) -> 661760.25 | C10: =SUMPRODUCT(((Clean_Data!H2:H301=$B$5)+($B$5="All"))*((Clean_Data!G2:G301=$E$5)+($E$5="All"))*((Clean_Data!I2:I301=$B$6)+($B$6="All"))*((Clean_Data!P2:P301=$E$6)+($E$6="All"))*(Clean_Data!AH2:AH301="READY FOR REPORTING")*Clean_Data!T2:T301) -> 170908.25 | E10: =SUMPRODUCT(--((Clean_Data!H2:H301=$B$5)+($B$5="All")),--((Clean_Data!G2:G301=$E$5)+($E$5="All")),--((Clean_Data!I2:I301=$B$6)+($B$6="All")),--((Clean_Data!P2:P301=$E$6)+($E$6="All")),--(Clean_Data!AH2:AH301="READY FOR REPORTING")) -> 204 | G10: =SUMPRODUCT(((Clean_Data!H2:H301=$B$5)+($B$5="All"))*((Clean_Data!G2:G301=$E$5)+($E$5="All"))*((Clean_Data!I2:I301=$B$6)+($B$6="All"))*((Clean_Data!P2:P301=$E$6)+($E$6="All"))*(Clean_Data!AH2:AH301="READY FOR REPORTING")*Clean_Data!K2:K301) -> 1322 | I10: =IFERROR(A10/E10,0) -> 3243.9228 | K10: =IFERROR(SUMPRODUCT(((Clean_Data!H2:H301=$B$5)+($B$5="All"))*((Clean_Data!G2:G301=$E$5)+($E$5="All"))*((Clean_Data!I2:I301=$B$6)+($B$6="All"))*((Clean_Data!P2:P301=$E$6)+($E$6="All"))*(Clean_Data!AH2:AH301="READY FOR REPORTING")*Clean_Data!N2:N301)/E10,0) -> 0.080392157
A14: Region | B14: Revenue | C14: Profit | D14: Orders | F14: Category | G14: Revenue | H14: Profit | I14: Orders
A15: Bucharest | B15: =SUMIFS(Clean_Data!R2:R301,Clean_Data!H2:H301,A15,Clean_Data!AH2:AH301,"READY FOR REPORTING",Clean_Data!P2:P301,$E$6) -> 84871 | C15: =SUMIFS(Clean_Data!T2:T301,Clean_Data!H2:H301,A15,Clean_Data!AH2:AH301,"READY FOR REPORTING",Clean_Data!P2:P301,$E$6) -> 22597 | D15: =COUNTIFS(Clean_Data!H2:H301,A15,Clean_Data!AH2:AH301,"READY FOR REPORTING",Clean_Data!P2:P301,$E$6) -> 36 | F15: Accessories | G15: =SUMIFS(Clean_Data!R2:R301,Clean_Data!G2:G301,F15,Clean_Data!AH2:AH301,"READY FOR REPORTING",Clean_Data!P2:P301,$E$6) -> 66527 | H15: =SUMIFS(Clean_Data!T2:T301,Clean_Data!G2:G301,F15,Clean_Data!AH2:AH301,"READY FOR REPORTING",Clean_Data!P2:P301,$E$6) -> 25449 | I15: =COUNTIFS(Clean_Data!G2:G301,F15,Clean_Data!AH2:AH301,"READY FOR REPORTING",Clean_Data!P2:P301,$E$6) -> 72
A16: North | B16: =SUMIFS(Clean_Data!R2:R301,Clean_Data!H2:H301,A16,Clean_Data!AH2:AH301,"READY FOR REPORTING",Clean_Data!P2:P301,$E$6) -> 121630.25 | C16: =SUMIFS(Clean_Data!T2:T301,Clean_Data!H2:H301,A16,Clean_Data!AH2:AH301,"READY FOR REPORTING",Clean_Data!P2:P301,$E$6) -> 32267.25 | D16: =COUNTIFS(Clean_Data!H2:H301,A16,Clean_Data!AH2:AH301,"READY FOR REPORTING",Clean_Data!P2:P301,$E$6) -> 36 | F16: Electronics | G16: =SUMIFS(Clean_Data!R2:R301,Clean_Data!G2:G301,F16,Clean_Data!AH2:AH301,"READY FOR REPORTING",Clean_Data!P2:P301,$E$6) -> 257639.75 | H16: =SUMIFS(Clean_Data!T2:T301,Clean_Data!G2:G301,F16,Clean_Data!AH2:AH301,"READY FOR REPORTING",Clean_Data!P2:P301,$E$6) -> 67695.75 | I16: =COUNTIFS(Clean_Data!G2:G301,F16,Clean_Data!AH2:AH301,"READY FOR REPORTING",Clean_Data!P2:P301,$E$6) -> 82
A17: South | B17: =SUMIFS(Clean_Data!R2:R301,Clean_Data!H2:H301,A17,Clean_Data!AH2:AH301,"READY FOR REPORTING",Clean_Data!P2:P301,$E$6) -> 194550.75 | C17: =SUMIFS(Clean_Data!T2:T301,Clean_Data!H2:H301,A17,Clean_Data!AH2:AH301,"READY FOR REPORTING",Clean_Data!P2:P301,$E$6) -> 49004.75 | D17: =COUNTIFS(Clean_Data!H2:H301,A17,Clean_Data!AH2:AH301,"READY FOR REPORTING",Clean_Data!P2:P301,$E$6) -> 46 | F17: Furniture | G17: =SUMIFS(Clean_Data!R2:R301,Clean_Data!G2:G301,F17,Clean_Data!AH2:AH301,"READY FOR REPORTING",Clean_Data!P2:P301,$E$6) -> 337593.5 | H17: =SUMIFS(Clean_Data!T2:T301,Clean_Data!G2:G301,F17,Clean_Data!AH2:AH301,"READY FOR REPORTING",Clean_Data!P2:P301,$E$6) -> 77763.5 | I17: =COUNTIFS(Clean_Data!G2:G301,F17,Clean_Data!AH2:AH301,"READY FOR REPORTING",Clean_Data!P2:P301,$E$6) -> 50
A18: East | B18: =SUMIFS(Clean_Data!R2:R301,Clean_Data!H2:H301,A18,Clean_Data!AH2:AH301,"READY FOR REPORTING",Clean_Data!P2:P301,$E$6) -> 147815.75 | C18: =SUMIFS(Clean_Data!T2:T301,Clean_Data!H2:H301,A18,Clean_Data!AH2:AH301,"READY FOR REPORTING",Clean_Data!P2:P301,$E$6) -> 36950.75 | D18: =COUNTIFS(Clean_Data!H2:H301,A18,Clean_Data!AH2:AH301,"READY FOR REPORTING",Clean_Data!P2:P301,$E$6) -> 41
A19: West | B19: =SUMIFS(Clean_Data!R2:R301,Clean_Data!H2:H301,A19,Clean_Data!AH2:AH301,"READY FOR REPORTING",Clean_Data!P2:P301,$E$6) -> 112892.5 | C19: =SUMIFS(Clean_Data!T2:T301,Clean_Data!H2:H301,A19,Clean_Data!AH2:AH301,"READY FOR REPORTING",Clean_Data!P2:P301,$E$6) -> 30088.5 | D19: =COUNTIFS(Clean_Data!H2:H301,A19,Clean_Data!AH2:AH301,"READY FOR REPORTING",Clean_Data!P2:P301,$E$6) -> 45

Sheet Target_vs_Actual
A1: SALES TARGET VS ACTUAL ANALYSIS
A4: Month | B4: Region | C4: Revenue_Target | D4: Actual_Revenue | E4: Revenue_Variance | F4: Revenue_Achievement | G4: Profit_Target | H4: Actual_Profit | I4: Profit_Variance | J4: Profit_Achievement | L4: Region | M4: Revenue Target | N4: Actual Revenue | O4: Variance | P4: Achievement | Q4: Status
A5: 45658 | B5: Bucharest | C5: 8950 | D5: =SUMIFS(Clean_Data!$R$2:$R$301,Clean_Data!$B$2:$B$301,">="&A5,Clean_Data!$B$2:$B$301,"<"&EDATE(A5,1),Clean_Data!$H$2:$H$301,B5,Clean_Data!$V$2:$V$301,"VALID",Clean_Data!$P$2:$P$301,"Completed") -> 16815.75 | E5: =D5-C5 -> 7865.75 | F5: =IFERROR(D5/C5,0) -> 1.8788547 | G5: 1969 | H5: =SUMIFS(Clean_Data!$T$2:$T$301,Clean_Data!$B$2:$B$301,">="&A5,Clean_Data!$B$2:$B$301,"<"&EDATE(A5,1),Clean_Data!$H$2:$H$301,B5,Clean_Data!$V$2:$V$301,"VALID",Clean_Data!$P$2:$P$301,"Completed") -> 4279.75 | I5: =H5-G5 -> 2310.75 | J5: =IFERROR(H5/G5,0) -> 2.1735653 | L5: Bucharest | M5: =SUMIF($B$5:$B$64,L5,$C$5:$C$64) -> 137100 | N5: =SUMIF($B$5:$B$64,L5,$D$5:$D$64) -> 84871 | O5: =N5-M5 -> -52229 | P5: =IFERROR(N5/M5,0) -> 0.61904449 | Q5: =IF(P5>=1,"Target Met","Below Target") -> Below Target
A6: 45658 | B6: North | C6: 9600 | D6: =SUMIFS(Clean_Data!$R$2:$R$301,Clean_Data!$B$2:$B$301,">="&A6,Clean_Data!$B$2:$B$301,"<"&EDATE(A6,1),Clean_Data!$H$2:$H$301,B6,Clean_Data!$V$2:$V$301,"VALID",Clean_Data!$P$2:$P$301,"Completed") -> 4947.5 | E6: =D6-C6 -> -4652.5 | F6: =IFERROR(D6/C6,0) -> 0.51536458 | G6: 2160 | H6: =SUMIFS(Clean_Data!$T$2:$T$301,Clean_Data!$B$2:$B$301,">="&A6,Clean_Data!$B$2:$B$301,"<"&EDATE(A6,1),Clean_Data!$H$2:$H$301,B6,Clean_Data!$V$2:$V$301,"VALID",Clean_Data!$P$2:$P$301,"Completed") -> 1844.5 | I6: =H6-G6 -> -315.5 | J6: =IFERROR(H6/G6,0) -> 0.85393519 | L6: North | M6: =SUMIF($B$5:$B$64,L6,$C$5:$C$64) -> 144900 | N6: =SUMIF($B$5:$B$64,L6,$D$5:$D$64) -> 121630.25 | O6: =N6-M6 -> -23269.75 | P6: =IFERROR(N6/M6,0) -> 0.83940821 | Q6: =IF(P6>=1,"Target Met","Below Target") -> Below Target
A7: 45658 | B7: South | C7: 10250 | D7: =SUMIFS(Clean_Data!$R$2:$R$301,Clean_Data!$B$2:$B$301,">="&A7,Clean_Data!$B$2:$B$301,"<"&EDATE(A7,1),Clean_Data!$H$2:$H$301,B7,Clean_Data!$V$2:$V$301,"VALID",Clean_Data!$P$2:$P$301,"Completed") -> 11497.5 | E7: =D7-C7 -> 1247.5 | F7: =IFERROR(D7/C7,0) -> 1.1217073 | G7: 2357.5 | H7: =SUMIFS(Clean_Data!$T$2:$T$301,Clean_Data!$B$2:$B$301,">="&A7,Clean_Data!$B$2:$B$301,"<"&EDATE(A7,1),Clean_Data!$H$2:$H$301,B7,Clean_Data!$V$2:$V$301,"VALID",Clean_Data!$P$2:$P$301,"Completed") -> 2157.5 | I7: =H7-G7 -> -200 | J7: =IFERROR(H7/G7,0) -> 0.91516437 | L7: South | M7: =SUMIF($B$5:$B$64,L7,$C$5:$C$64) -> 152700 | N7: =SUMIF($B$5:$B$64,L7,$D$5:$D$64) -> 194550.75 | O7: =N7-M7 -> 41850.75 | P7: =IFERROR(N7/M7,0) -> 1.2740717 | Q7: =IF(P7>=1,"Target Met","Below Target") -> Target Met
A8: 45658 | B8: East | C8: 10900 | D8: =SUMIFS(Clean_Data!$R$2:$R$301,Clean_Data!$B$2:$B$301,">="&A8,Clean_Data!$B$2:$B$301,"<"&EDATE(A8,1),Clean_Data!$H$2:$H$301,B8,Clean_Data!$V$2:$V$301,"VALID",Clean_Data!$P$2:$P$301,"Completed") -> 14004.5 | E8: =D8-C8 -> 3104.5 | F8: =IFERROR(D8/C8,0) -> 1.2848165 | G8: 2561.5 | H8: =SUMIFS(Clean_Data!$T$2:$T$301,Clean_Data!$B$2:$B$301,">="&A8,Clean_Data!$B$2:$B$301,"<"&EDATE(A8,1),Clean_Data!$H$2:$H$301,B8,Clean_Data!$V$2:$V$301,"VALID",Clean_Data!$P$2:$P$301,"Completed") -> 3774.5 | I8: =H8-G8 -> 1213 | J8: =IFERROR(H8/G8,0) -> 1.4735507 | L8: East | M8: =SUMIF($B$5:$B$64,L8,$C$5:$C$64) -> 160500 | N8: =SUMIF($B$5:$B$64,L8,$D$5:$D$64) -> 147815.75 | O8: =N8-M8 -> -12684.25 | P8: =IFERROR(N8/M8,0) -> 0.9209704 | Q8: =IF(P8>=1,"Target Met","Below Target") -> Below Target
A9: 45658 | B9: West | C9: 11550 | D9: =SUMIFS(Clean_Data!$R$2:$R$301,Clean_Data!$B$2:$B$301,">="&A9,Clean_Data!$B$2:$B$301,"<"&EDATE(A9,1),Clean_Data!$H$2:$H$301,B9,Clean_Data!$V$2:$V$301,"VALID",Clean_Data!$P$2:$P$301,"Completed") -> 0 | E9: =D9-C9 -> -11550 | F9: =IFERROR(D9/C9,0) -> 0 | G9: 2772 | H9: =SUMIFS(Clean_Data!$T$2:$T$301,Clean_Data!$B$2:$B$301,">="&A9,Clean_Data!$B$2:$B$301,"<"&EDATE(A9,1),Clean_Data!$H$2:$H$301,B9,Clean_Data!$V$2:$V$301,"VALID",Clean_Data!$P$2:$P$301,"Completed") -> 0 | I9: =H9-G9 -> -2772 | J9: =IFERROR(H9/G9,0) -> 0 | L9: West | M9: =SUMIF($B$5:$B$64,L9,$C$5:$C$64) -> 168300 | N9: =SUMIF($B$5:$B$64,L9,$D$5:$D$64) -> 112892.5 | O9: =N9-M9 -> -55407.5 | P9: =IFERROR(N9/M9,0) -> 0.67078134 | Q9: =IF(P9>=1,"Target Met","Below Target") -> Below Target
A10: 45689 | B10: Bucharest | C10: 9400 | D10: =SUMIFS(Clean_Data!$R$2:$R$301,Clean_Data!$B$2:$B$301,">="&A10,Clean_Data!$B$2:$B$301,"<"&EDATE(A10,1),Clean_Data!$H$2:$H$301,B10,Clean_Data!$V$2:$V$301,"VALID",Clean_Data!$P$2:$P$301,"Completed") -> 3024 | E10: =D10-C10 -> -6376 | F10: =IFERROR(D10/C10,0) -> 0.32170213 | G10: 2068 | H10: =SUMIFS(Clean_Data!$T$2:$T$301,Clean_Data!$B$2:$B$301,">="&A10,Clean_Data!$B$2:$B$301,"<"&EDATE(A10,1),Clean_Data!$H$2:$H$301,B10,Clean_Data!$V$2:$V$301,"VALID",Clean_Data!$P$2:$P$301,"Completed") -> 664 | I10: =H10-G10 -> -1404 | J10: =IFERROR(H10/G10,0) -> 0.32108317
A11: 45689 | B11: North | C11: 10050 | D11: =SUMIFS(Clean_Data!$R$2:$R$301,Clean_Data!$B$2:$B$301,">="&A11,Clean_Data!$B$2:$B$301,"<"&EDATE(A11,1),Clean_Data!$H$2:$H$301,B11,Clean_Data!$V$2:$V$301,"VALID",Clean_Data!$P$2:$P$301,"Completed") -> 26663 | E11: =D11-C11 -> 16613 | F11: =IFERROR(D11/C11,0) -> 2.6530348 | G11: 2261.25 | H11: =SUMIFS(Clean_Data!$T$2:$T$301,Clean_Data!$B$2:$B$301,">="&A11,Clean_Data!$B$2:$B$301,"<"&EDATE(A11,1),Clean_Data!$H$2:$H$301,B11,Clean_Data!$V$2:$V$301,"VALID",Clean_Data!$P$2:$P$301,"Completed") -> 7098 | I11: =H11-G11 -> 4836.75 | J11: =IFERROR(H11/G11,0) -> 3.1389718
A12: 45689 | B12: South | C12: 10700 | D12: =SUMIFS(Clean_Data!$R$2:$R$301,Clean_Data!$B$2:$B$301,">="&A12,Clean_Data!$B$2:$B$301,"<"&EDATE(A12,1),Clean_Data!$H$2:$H$301,B12,Clean_Data!$V$2:$V$301,"VALID",Clean_Data!$P$2:$P$301,"Completed") -> 12053.25 | E12: =D12-C12 -> 1353.25 | F12: =IFERROR(D12/C12,0) -> 1.126472 | G12: 2461 | H12: =SUMIFS(Clean_Data!$T$2:$T$301,Clean_Data!$B$2:$B$301,">="&A12,Clean_Data!$B$2:$B$301,"<"&EDATE(A12,1),Clean_Data!$H$2:$H$301,B12,Clean_Data!$V$2:$V$301,"VALID",Clean_Data!$P$2:$P$301,"Completed") -> 2967.25 | I12: =H12-G12 -> 506.25 | J12: =IFERROR(H12/G12,0) -> 1.2057091
A13: 45689 | B13: East | C13: 11350 | D13: =SUMIFS(Clean_Data!$R$2:$R$301,Clean_Data!$B$2:$B$301,">="&A13,Clean_Data!$B$2:$B$301,"<"&EDATE(A13,1),Clean_Data!$H$2:$H$301,B13,Clean_Data!$V$2:$V$301,"VALID",Clean_Data!$P$2:$P$301,"Completed") -> 0 | E13: =D13-C13 -> -11350 | F13: =IFERROR(D13/C13,0) -> 0 | G13: 2667.25 | H13: =SUMIFS(Clean_Data!$T$2:$T$301,Clean_Data!$B$2:$B$301,">="&A13,Clean_Data!$B$2:$B$301,"<"&EDATE(A13,1),Clean_Data!$H$2:$H$301,B13,Clean_Data!$V$2:$V$301,"VALID",Clean_Data!$P$2:$P$301,"Completed") -> 0 | I13: =H13-G13 -> -2667.25 | J13: =IFERROR(H13/G13,0) -> 0
A14: 45689 | B14: West | C14: 12000 | D14: =SUMIFS(Clean_Data!$R$2:$R$301,Clean_Data!$B$2:$B$301,">="&A14,Clean_Data!$B$2:$B$301,"<"&EDATE(A14,1),Clean_Data!$H$2:$H$301,B14,Clean_Data!$V$2:$V$301,"VALID",Clean_Data!$P$2:$P$301,"Completed") -> 1398 | E14: =D14-C14 -> -10602 | F14: =IFERROR(D14/C14,0) -> 0.1165 | G14: 2880 | H14: =SUMIFS(Clean_Data!$T$2:$T$301,Clean_Data!$B$2:$B$301,">="&A14,Clean_Data!$B$2:$B$301,"<"&EDATE(A14,1),Clean_Data!$H$2:$H$301,B14,Clean_Data!$V$2:$V$301,"VALID",Clean_Data!$P$2:$P$301,"Completed") -> 513 | I14: =H14-G14 -> -2367 | J14: =IFERROR(H14/G14,0) -> 0.178125
A15: 45717 | B15: Bucharest | C15: 9850 | D15: =SUMIFS(Clean_Data!$R$2:$R$301,Clean_Data!$B$2:$B$301,">="&A15,Clean_Data!$B$2:$B$301,"<"&EDATE(A15,1),Clean_Data!$H$2:$H$301,B15,Clean_Data!$V$2:$V$301,"VALID",Clean_Data!$P$2:$P$301,"Completed") -> 5823 | E15: =D15-C15 -> -4027 | F15: =IFERROR(D15/C15,0) -> 0.59116751 | G15: 2167 | H15: =SUMIFS(Clean_Data!$T$2:$T$301,Clean_Data!$B$2:$B$301,">="&A15,Clean_Data!$B$2:$B$301,"<"&EDATE(A15,1),Clean_Data!$H$2:$H$301,B15,Clean_Data!$V$2:$V$301,"VALID",Clean_Data!$P$2:$P$301,"Completed") -> 1581 | I15: =H15-G15 -> -586 | J15: =IFERROR(H15/G15,0) -> 0.72958006
A16: 45717 | B16: North | C16: 10500 | D16: =SUMIFS(Clean_Data!$R$2:$R$301,Clean_Data!$B$2:$B$301,">="&A16,Clean_Data!$B$2:$B$301,"<"&EDATE(A16,1),Clean_Data!$H$2:$H$301,B16,Clean_Data!$V$2:$V$301,"VALID",Clean_Data!$P$2:$P$301,"Completed") -> 19485.5 | E16: =D16-C16 -> 8985.5 | F16: =IFERROR(D16/C16,0) -> 1.8557619 | G16: 2362.5 | H16: =SUMIFS(Clean_Data!$T$2:$T$301,Clean_Data!$B$2:$B$301,">="&A16,Clean_Data!$B$2:$B$301,"<"&EDATE(A16,1),Clean_Data!$H$2:$H$301,B16,Clean_Data!$V$2:$V$301,"VALID",Clean_Data!$P$2:$P$301,"Completed") -> 5013.5 | I16: =H16-G16 -> 2651 | J16: =IFERROR(H16/G16,0) -> 2.1221164
A17: 45717 | B17: South | C17: 11150 | D17: =SUMIFS(Clean_Data!$R$2:$R$301,Clean_Data!$B$2:$B$301,">="&A17,Clean_Data!$B$2:$B$301,"<"&EDATE(A17,1),Clean_Data!$H$2:$H$301,B17,Clean_Data!$V$2:$V$301,"VALID",Clean_Data!$P$2:$P$301,"Completed") -> 3309.5 | E17: =D17-C17 -> -7840.5 | F17: =IFERROR(D17/C17,0) -> 0.29681614 | G17: 2564.5 | H17: =SUMIFS(Clean_Data!$T$2:$T$301,Clean_Data!$B$2:$B$301,">="&A17,Clean_Data!$B$2:$B$301,"<"&EDATE(A17,1),Clean_Data!$H$2:$H$301,B17,Clean_Data!$V$2:$V$301,"VALID",Clean_Data!$P$2:$P$301,"Completed") -> 1424.5 | I17: =H17-G17 -> -1140 | J17: =IFERROR(H17/G17,0) -> 0.5554689
A18: 45717 | B18: East | C18: 11800 | D18: =SUMIFS(Clean_Data!$R$2:$R$301,Clean_Data!$B$2:$B$301,">="&A18,Clean_Data!$B$2:$B$301,"<"&EDATE(A18,1),Clean_Data!$H$2:$H$301,B18,Clean_Data!$V$2:$V$301,"VALID",Clean_Data!$P$2:$P$301,"Completed") -> 0 | E18: =D18-C18 -> -11800 | F18: =IFERROR(D18/C18,0) -> 0 | G18: 2773 | H18: =SUMIFS(Clean_Data!$T$2:$T$301,Clean_Data!$B$2:$B$301,">="&A18,Clean_Data!$B$2:$B$301,"<"&EDATE(A18,1),Clean_Data!$H$2:$H$301,B18,Clean_Data!$V$2:$V$301,"VALID",Clean_Data!$P$2:$P$301,"Completed") -> 0 | I18: =H18-G18 -> -2773 | J18: =IFERROR(H18/G18,0) -> 0
A19: 45717 | B19: West | C19: 12450 | D19: =SUMIFS(Clean_Data!$R$2:$R$301,Clean_Data!$B$2:$B$301,">="&A19,Clean_Data!$B$2:$B$301,"<"&EDATE(A19,1),Clean_Data!$H$2:$H$301,B19,Clean_Data!$V$2:$V$301,"VALID",Clean_Data!$P$2:$P$301,"Completed") -> 3198 | E19: =D19-C19 -> -9252 | F19: =IFERROR(D19/C19,0) -> 0.25686747 | G19: 2988 | H19: =SUMIFS(Clean_Data!$T$2:$T$301,Clean_Data!$B$2:$B$301,">="&A19,Clean_Data!$B$2:$B$301,"<"&EDATE(A19,1),Clean_Data!$H$2:$H$301,B19,Clean_Data!$V$2:$V$301,"VALID",Clean_Data!$P$2:$P$301,"Completed") -> 1203 | I19: =H19-G19 -> -1785 | J19: =IFERROR(H19/G19,0) -> 0.40261044
A20: 45748 | B20: Bucharest | C20: 10300 | D20: =SUMIFS(Clean_Data!$R$2:$R$301,Clean_Data!$B$2:$B$301,">="&A20,Clean_Data!$B$2:$B$301,"<"&EDATE(A20,1),Clean_Data!$H$2:$H$301,B20,Clean_Data!$V$2:$V$301,"VALID",Clean_Data!$P$2:$P$301,"Completed") -> 9684 | E20: =D20-C20 -> -616 | F20: =IFERROR(D20/C20,0) -> 0.94019417 | G20: 2266 | H20: =SUMIFS(Clean_Data!$T$2:$T$301,Clean_Data!$B$2:$B$301,">="&A20,Clean_Data!$B$2:$B$301,"<"&EDATE(A20,1),Clean_Data!$H$2:$H$301,B20,Clean_Data!$V$2:$V$301,"VALID",Clean_Data!$P$2:$P$301,"Completed") -> 1834 | I20: =H20-G20 -> -432 | J20: =IFERROR(H20/G20,0) -> 0.80935569
A21: 45748 | B21: North | C21: 10950 | D21: =SUMIFS(Clean_Data!$R$2:$R$301,Clean_Data!$B$2:$B$301,">="&A21,Clean_Data!$B$2:$B$301,"<"&EDATE(A21,1),Clean_Data!$H$2:$H$301,B21,Clean_Data!$V$2:$V$301,"VALID",Clean_Data!$P$2:$P$301,"Completed") -> 1248 | E21: =D21-C21 -> -9702 | F21: =IFERROR(D21/C21,0) -> 0.1139726 | G21: 2463.75 | H21: =SUMIFS(Clean_Data!$T$2:$T$301,Clean_Data!$B$2:$B$301,">="&A21,Clean_Data!$B$2:$B$301,"<"&EDATE(A21,1),Clean_Data!$H$2:$H$301,B21,Clean_Data!$V$2:$V$301,"VALID",Clean_Data!$P$2:$P$301,"Completed") -> 408 | I21: =H21-G21 -> -2055.75 | J21: =IFERROR(H21/G21,0) -> 0.16560122
... A64: 45992 | B64: West | C64: 16500 | D64: =SUMIFS(Clean_Data!$R$2:$R$301,Clean_Data!$B$2:$B$301,">="&A64,Clean_Data!$B$2:$B$301,"<"&EDATE(A64,1),Clean_Data!$H$2:$H$301,B64,Clean_Data!$V$2:$V$301,"VALID",Clean_Data!$P$2:$P$301,"Completed") -> 11159.5 | E64: =D64-C64 -> -5340.5 | F64: =IFERROR(D64/C64,0) -> 0.67633333 | G64: 3960 | H64: =SUMIFS(Clean_Data!$T$2:$T$301,Clean_Data!$B$2:$B$301,">="&A64,Clean_Data!$B$2:$B$301,"<"&EDATE(A64,1),Clean_Data!$H$2:$H$301,B64,Clean_Data!$V$2:$V$301,"VALID",Clean_Data!$P$2:$P$301,"Completed") -> 3677.5 | I64: =H64-G64 -> -282.5 | J64: =IFERROR(H64/G64,0) -> 0.92866162

Sheet Quality_Checklist
A1: DATA QUALITY CHECKLIST
A4: Check | B4: Result | C4: Status | D4: Severity | E4: Meaning
A5: Missing Order IDs | B5: =COUNTBLANK(Clean_Data!A2:A301) -> 0 | C5: =IF(B5=0,"PASS","CHECK") -> PASS | D5: Critical | E5: Every order needs an ID
A6: Duplicate Order IDs | B6: =SUMPRODUCT(--(Clean_Data!A2:A301<>""),--(COUNTIF(Clean_Data!A2:A301,Clean_Data!A2:A301)>1)) -> 2 | C6: =IF(B6=0,"PASS","CHECK") -> CHECK | D6: Critical | E6: Duplicate transactions may be counted twice
A7: Missing Customer IDs | B7: =COUNTBLANK(Clean_Data!C2:C301) -> 0 | C7: =IF(B7=0,"PASS","CHECK") -> PASS | D7: High | E7: Orders must link to customers
A8: Invalid Emails | B8: =COUNTIF(Clean_Data!AG2:AG301,"Invalid Email") -> 2 | C8: =IF(B8=0,"PASS","CHECK") -> CHECK | D8: Medium | E8: Basic contact format check
A9: Unknown Products | B9: =COUNTIF(Clean_Data!AD2:AD301,"Product Not Found") -> 1 | C9: =IF(B9=0,"PASS","CHECK") -> CHECK | D9: Critical | E9: Product must exist in master data
A10: Price Mismatches | B10: =COUNTIF(Clean_Data!AF2:AF301,"Price Mismatch") -> 1 | C10: =IF(B10=0,"PASS","CHECK") -> CHECK | D10: High | E10: Selling price differs from approved price
A11: Invalid Quantities | B11: =COUNTIF(Clean_Data!K2:K301,"<"&Settings!$B$12) -> 1 | C11: =IF(B11=0,"PASS","CHECK") -> CHECK | D11: Critical | E11: Quantity must meet minimum
A12: High Discounts | B12: =COUNTIF(Clean_Data!N2:N301,">"&Settings!$B$8) -> 1 | C12: =IF(B12=0,"PASS","CHECK") -> CHECK | D12: Medium | E12: Discount exceeds normal threshold
A13: Loss-making Orders | B13: =COUNTIF(Clean_Data!AC2:AC301,"Loss") -> 2 | C13: =IF(B13=0,"PASS","CHECK") -> CHECK | D13: High | E13: Order generated a negative profit
A14: Records Requiring Review | B14: =COUNTIF(Clean_Data!AH2:AH301,"REVIEW REQUIRED") -> 9 | C14: =IF(B14=0,"PASS","CHECK") -> CHECK | D14: High | E14: Final validation did not pass
A15: Missing Order Dates | B15: =COUNTBLANK(Clean_Data!B2:B301) -> 0 | C15: =IF(B15=0,"PASS","CHECK") -> PASS | D15: Critical | E15: Every transaction requires a valid order date
A16: Invalid Unit Prices | B16: =COUNTIF(Clean_Data!L2:L301,"<=0") -> 1 | C16: =IF(B16=0,"PASS","CHECK") -> CHECK | D16: Critical | E16: Unit price must be greater than zero
A17: Invalid Revenue | B17: =COUNTIF(Clean_Data!Q2:R301,"<0") -> 3 | C17: =IF(B17=0,"PASS","CHECK") -> CHECK | D17: Critical | E17: Gross and net revenue cannot be negative
A20: Quality Metric
A21: Total Records | B21: =COUNTA(Clean_Data!A2:A301) -> 300
A22: Checks Passed | B22: =COUNTIF(C5:C17,"PASS") -> 3
A23: Checks Failed | B23: =COUNTIF(C5:C17,"CHECK") -> 10
A24: Quality Score (%) | B24: =IF(COUNTA(A5:A17)=0,0,B22/COUNTA(A5:A17)) -> 0.23076923
A25: Overall Status | B25: =IF(B23=0,"PASS","CHECK") -> CHECK
A26: Last Refresh | B26: =TODAY() -> 46214

Sheet Error_Report
A1: DATA QUALITY ERROR REPORT
A4: Source_Row | B4: Order_ID | C4: Field_or_Rule | D4: Invalid_Value | E4: Error_Type | F4: Severity | G4: Recommended_Action | H4: Status
A5: 11 | B5: ORD-10010 | C5: Customer_Email | D5: invalid-email | E5: Invalid email format | F5: Medium | G5: Correct the email address | H5: Open
A6: 26 | B6: ORD-10025 | C6: Quantity | D6: 0 | E6: Invalid quantity | F6: Critical | G6: Quantity must be greater than zero | H6: Open
A7: 50 | B7: ORD-10049 | C7: Product_ID | D7: UNKNOWN | E7: Unknown product | F7: Critical | G7: Match against product master | H7: Open
A8: 74 | B8: ORD-10073 | C8: Region | E8: Missing region | F8: High | G8: Select an approved region | H8: Open
A9: 97 | B9: ORD-10096 | C9: Discount_Rate | D9: 1.25 | E9: Discount outside approved range | F9: High | G9: Use a value between 0% and 50% | H9: Open
A10: 121 | B10: ORD-10120 | C10: Unit_Price | D10: -50 | E10: Negative price | F10: Critical | G10: Price must be zero or positive | H10: Open
A11: 145 | B11: ORD-10144 | C11: Customer_ID | E11: Missing customer ID | F11: High | G11: Identify the correct customer | H11: Open
A12: 169 | B12: ORD-10168 | C12: Order_Status | D12: Pending | E12: Unapproved order status | F12: High | G12: Choose Completed, Returned or Cancelled | H12: Open
A13: 203 | B13: ORD-10201 | C13: Order_ID | D13: ORD-10201 | E13: Duplicate Order ID | F13: Critical | G13: Verify against source row 202 | H13: Open
A14: 227 | B14: ORD-10226 | C14: Product_Name | E14: Missing product name | F14: High | G14: Populate from product master | H14: Open
A15: 262 | C15: Order_ID | E15: Missing Order ID | F15: Critical | G15: Enter a unique order ID | H15: Open
A16: 282 | B16: ORD-10281 | C16: Customer_Email | D16: customer@ | E16: Invalid email format | F16: Medium | G16: Correct the email address | H16: Open

Sheet Clean_Data
A1: Order_ID | B1: Order_Date | C1: Customer_ID | D1: Customer_Email | E1: Product_ID | F1: Product_Name | G1: Category | H1: Region | I1: Sales_Channel | J1: Sales_Representative | K1: Quantity | L1: Unit_Price | M1: Unit_Cost | N1: Discount_Rate | O1: Payment_Method | P1: Order_Status | Q1: Gross_Revenue | R1: Net_Revenue | S1: Total_Cost | T1: Profit | U1: Profit_Margin | V1: Validation_Status | W1: Error_Details | X1: Order_Month | Y1: Order_Quarter | Z1: Customer_Segment | AA1: Order_Value_Band | AB1: Discount_Band | AC1: Profit_Status | AD1: Product_Lookup_Name | AE1: Product_Lookup_Category | AF1: Price_Check | AG1: Email_Check | AH1: Final_Record_Status | AI1: Order_ID_Format_Check | AJ1: Customer_ID_Format_Check | AK1: Customer_Master_Check | AL1: Margin_Target_Check | AM1: Date_Year_Check | AN1: Complete_Check_Count
A2: =Raw_Data!A2 -> ORD-10001 | B2: =Raw_Data!B2 -> 45670 | C2: =Raw_Data!C2 -> C1029 | D2: =Raw_Data!D2 -> client36@example.com | E2: =Raw_Data!E2 -> P1002 | F2: =Raw_Data!F2 -> Wireless Mouse | G2: =Raw_Data!G2 -> Accessories | H2: =Raw_Data!H2 -> Bucharest | ... P2: =Raw_Data!P2 -> Completed | Q2: =K2*L2 -> 1020 | R2: =Q2*(1-N2) -> 969 | S2: =K2*M2 -> 528 | T2: =R2-S2 -> 441 | U2: =IFERROR(T2/R2,0) -> 0.45510836 | V2: =IF(OR(A2="",COUNTIF($A$2:$A$301,A2)>1,C2="",D2="",ISERROR(SEARCH("@",D2)),ISERROR(SEARCH(".",D2)),COUNTIF(Lookups!$A$2:$A$11,E2)=0,F2="",H2="",K2<=0,L2<0,M2<0,N2<0,N2>0.5,COUNTIF(Lookups!$K$2:$K$4,P2)=0),"ERROR","VALID") -> VALID | W2: =IF(A2="","Missing Order ID; ","")&IF(COUNTIF($A$2:$A$301,A2)>1,"Duplicate Order ID; ","")&IF(C2="","Missing Customer ID; ","")&IF(OR(D2="",ISERROR(SEARCH("@",D2)),ISERROR(SEARCH(".",D2))),"Invalid Email; ","")&IF(COUNTIF(Lookups!$A$2:$A$11,E2)=0,"Unknown Product; ","")&IF(F2="","Missing Product Name; ","")&IF(H2="","Missing Region; ","")&IF(K2<=0,"Invalid Quantity; ","")&IF(L2<0,"Invalid Price; ","")&IF(M2<0,"Invalid Cost; ","")&IF(OR(N2<0,N2>0.5),"Invalid Discount; ","")&IF(COUNTIF(Lookups!$K$2:$K$4,P2)=0,"Invalid Status; ","") | X2: =TEXT(B2,"yyyy-mm") -> 2025-01 | Y2: ="Q"&ROUNDUP(MONTH(B2)/3,0) -> Q1 | Z2: =IF(R2>=Settings!$B$9,"High Value Customer",IF(R2>=Settings!$B$10,"Medium Value Customer","Standard Customer")) -> Standard Customer | AA2: =IF(R2>=Settings!$B$9,"Large Order",IF(R2>=Settings!$B$10,"Medium Order","Small Order")) -> Small Order | AB2: =IF(N2=0,"No Discount",IF(N2<=0.1,"Low Discount",IF(N2<=Settings!$B$8,"Medium Discount","High Discount"))) -> Low Discount | AC2: =IF(T2>0,"Profitable",IF(T2=0,"Break-even","Loss")) -> Profitable | AD2: =IFERROR(VLOOKUP(E2,Lookups!$A$2:$E$11,2,FALSE),"Product Not Found") -> Wireless Mouse | AE2: =IFERROR(VLOOKUP(E2,Lookups!$A$2:$E$11,3,FALSE),"Category Not Found") -> Accessories | AF2: =IFERROR(IF(L2=VLOOKUP(E2,Lookups!$A$2:$E$11,4,FALSE),"Price OK","Price Mismatch"),"Product Missing") -> Price OK | AG2: =IF(AND(ISNUMBER(SEARCH("@",D2)),ISNUMBER(SEARCH(".",D2))),"Valid Email","Invalid Email") -> Valid Email | AH2: =IF(AND(V2="VALID",AF2="Price OK",AG2="Valid Email"),"READY FOR REPORTING","REVIEW REQUIRED") -> READY FOR REPORTING | AI2: =IF(AND(LEFT(A2,LEN(Settings!$B$13))=Settings!$B$13,LEN(A2)=9),"Valid Format","Invalid Format") -> Valid Format | AJ2: =IF(LEFT(C2,LEN(Settings!$B$14))=Settings!$B$14,"Valid Format","Invalid Format") -> Valid Format | AK2: =IF(COUNTIF(Master_Data!$G$5:$G$14,C2)=1,"Known Customer","Customer Not in Master") -> Customer Not in Master | AL2: =IF(U2>=Settings!$B$11,"Target Met","Below Target") -> Target Met | AM2: =IF(YEAR(B2)=Settings!$B$5,"Correct Year","Wrong Year") -> Correct Year | AN2: =COUNTIF(AI2:AM2,"*Valid*")+COUNTIF(AI2:AM2,"Known Customer")+COUNTIF(AI2:AM2,"Target Met")+COUNTIF(AI2:AM2,"Correct Year") -> 4
A3: =Raw_Data!A3 -> ORD-10002 | B3: =Raw_Data!B3 -> 45874 | C3: =Raw_Data!C3 -> C1028 | D3: =Raw_Data!D3 -> client60@example.com | E3: =Raw_Data!E3 -> P1010 | F3: =Raw_Data!F3 -> Headset | G3: =Raw_Data!G3 -> Electronics | H3: =Raw_Data!H3 -> West | ... P3: =Raw_Data!P3 -> Completed | Q3: =K3*L3 -> 195 | R3: =Q3*(1-N3) -> 195 | S3: =K3*M3 -> 105 | T3: =R3-S3 -> 90 | U3: =IFERROR(T3/R3,0) -> 0.46153846 | V3: =IF(OR(A3="",COUNTIF($A$2:$A$301,A3)>1,C3="",D3="",ISERROR(SEARCH("@",D3)),ISERROR(SEARCH(".",D3)),COUNTIF(Lookups!$A$2:$A$11,E3)=0,F3="",H3="",K3<=0,L3<0,M3<0,N3<0,N3>0.5,COUNTIF(Lookups!$K$2:$K$4,P3)=0),"ERROR","VALID") -> VALID | W3: =IF(A3="","Missing Order ID; ","")&IF(COUNTIF($A$2:$A$301,A3)>1,"Duplicate Order ID; ","")&IF(C3="","Missing Customer ID; ","")&IF(OR(D3="",ISERROR(SEARCH("@",D3)),ISERROR(SEARCH(".",D3))),"Invalid Email; ","")&IF(COUNTIF(Lookups!$A$2:$A$11,E3)=0,"Unknown Product; ","")&IF(F3="","Missing Product Name; ","")&IF(H3="","Missing Region; ","")&IF(K3<=0,"Invalid Quantity; ","")&IF(L3<0,"Invalid Price; ","")&IF(M3<0,"Invalid Cost; ","")&IF(OR(N3<0,N3>0.5),"Invalid Discount; ","")&IF(COUNTIF(Lookups!$K$2:$K$4,P3)=0,"Invalid Status; ","") | X3: =TEXT(B3,"yyyy-mm") -> 2025-08 | Y3: ="Q"&ROUNDUP(MONTH(B3)/3,0) -> Q3 | Z3: =IF(R3>=Settings!$B$9,"High Value Customer",IF(R3>=Settings!$B$10,"Medium Value Customer","Standard Customer")) -> Standard Customer | AA3: =IF(R3>=Settings!$B$9,"Large Order",IF(R3>=Settings!$B$10,"Medium Order","Small Order")) -> Small Order | AB3: =IF(N3=0,"No Discount",IF(N3<=0.1,"Low Discount",IF(N3<=Settings!$B$8,"Medium Discount","High Discount"))) -> No Discount | AC3: =IF(T3>0,"Profitable",IF(T3=0,"Break-even","Loss")) -> Profitable | AD3: =IFERROR(VLOOKUP(E3,Lookups!$A$2:$E$11,2,FALSE),"Product Not Found") -> Headset | AE3: =IFERROR(VLOOKUP(E3,Lookups!$A$2:$E$11,3,FALSE),"Category Not Found") -> Electronics | AF3: =IFERROR(IF(L3=VLOOKUP(E3,Lookups!$A$2:$E$11,4,FALSE),"Price OK","Price Mismatch"),"Product Missing") -> Price OK | AG3: =IF(AND(ISNUMBER(SEARCH("@",D3)),ISNUMBER(SEARCH(".",D3))),"Valid Email","Invalid Email") -> Valid Email | AH3: =IF(AND(V3="VALID",AF3="Price OK",AG3="Valid Email"),"READY FOR REPORTING","REVIEW REQUIRED") -> READY FOR REPORTING | AI3: =IF(AND(LEFT(A3,LEN(Settings!$B$13))=Settings!$B$13,LEN(A3)=9),"Valid Format","Invalid Format") -> Valid Format | AJ3: =IF(LEFT(C3,LEN(Settings!$B$14))=Settings!$B$14,"Valid Format","Invalid Format") -> Valid Format | AK3: =IF(COUNTIF(Master_Data!$G$5:$G$14,C3)=1,"Known Customer","Customer Not in Master") -> Customer Not in Master | AL3: =IF(U3>=Settings!$B$11,"Target Met","Below Target") -> Target Met | AM3: =IF(YEAR(B3)=Settings!$B$5,"Correct Year","Wrong Year") -> Correct Year | AN3: =COUNTIF(AI3:AM3,"*Valid*")+COUNTIF(AI3:AM3,"Known Customer")+COUNTIF(AI3:AM3,"Target Met")+COUNTIF(AI3:AM3,"Correct Year") -> 4
A4: =Raw_Data!A4 -> ORD-10003 | B4: =Raw_Data!B4 -> 45872 | C4: =Raw_Data!C4 -> C1036 | D4: =Raw_Data!D4 -> client2@example.com | E4: =Raw_Data!E4 -> P1009 | F4: =Raw_Data!F4 -> Webcam | G4: =Raw_Data!G4 -> Electronics | H4: =Raw_Data!H4 -> North | ... P4: =Raw_Data!P4 -> Returned | Q4: =K4*L4 -> 920 | R4: =Q4*(1-N4) -> 828 | S4: =K4*M4 -> 528 | T4: =R4-S4 -> 300 | U4: =IFERROR(T4/R4,0) -> 0.36231884 | V4: =IF(OR(A4="",COUNTIF($A$2:$A$301,A4)>1,C4="",D4="",ISERROR(SEARCH("@",D4)),ISERROR(SEARCH(".",D4)),COUNTIF(Lookups!$A$2:$A$11,E4)=0,F4="",H4="",K4<=0,L4<0,M4<0,N4<0,N4>0.5,COUNTIF(Lookups!$K$2:$K$4,P4)=0),"ERROR","VALID") -> VALID | W4: =IF(A4="","Missing Order ID; ","")&IF(COUNTIF($A$2:$A$301,A4)>1,"Duplicate Order ID; ","")&IF(C4="","Missing Customer ID; ","")&IF(OR(D4="",ISERROR(SEARCH("@",D4)),ISERROR(SEARCH(".",D4))),"Invalid Email; ","")&IF(COUNTIF(Lookups!$A$2:$A$11,E4)=0,"Unknown Product; ","")&IF(F4="","Missing Product Name; ","")&IF(H4="","Missing Region; ","")&IF(K4<=0,"Invalid Quantity; ","")&IF(L4<0,"Invalid Price; ","")&IF(M4<0,"Invalid Cost; ","")&IF(OR(N4<0,N4>0.5),"Invalid Discount; ","")&IF(COUNTIF(Lookups!$K$2:$K$4,P4)=0,"Invalid Status; ","") | X4: =TEXT(B4,"yyyy-mm") -> 2025-08 | Y4: ="Q"&ROUNDUP(MONTH(B4)/3,0) -> Q3 | Z4: =IF(R4>=Settings!$B$9,"High Value Customer",IF(R4>=Settings!$B$10,"Medium Value Customer","Standard Customer")) -> Standard Customer | AA4: =IF(R4>=Settings!$B$9,"Large Order",IF(R4>=Settings!$B$10,"Medium Order","Small Order")) -> Small Order | AB4: =IF(N4=0,"No Discount",IF(N4<=0.1,"Low Discount",IF(N4<=Settings!$B$8,"Medium Discount","High Discount"))) -> Low Discount | AC4: =IF(T4>0,"Profitable",IF(T4=0,"Break-even","Loss")) -> Profitable | AD4: =IFERROR(VLOOKUP(E4,Lookups!$A$2:$E$11,2,FALSE),"Product Not Found") -> Webcam | AE4: =IFERROR(VLOOKUP(E4,Lookups!$A$2:$E$11,3,FALSE),"Category Not Found") -> Electronics | AF4: =IFERROR(IF(L4=VLOOKUP(E4,Lookups!$A$2:$E$11,4,FALSE),"Price OK","Price Mismatch"),"Product Missing") -> Price OK | AG4: =IF(AND(ISNUMBER(SEARCH("@",D4)),ISNUMBER(SEARCH(".",D4))),"Valid Email","Invalid Email") -> Valid Email | AH4: =IF(AND(V4="VALID",AF4="Price OK",AG4="Valid Email"),"READY FOR REPORTING","REVIEW REQUIRED") -> READY FOR REPORTING | AI4: =IF(AND(LEFT(A4,LEN(Settings!$B$13))=Settings!$B$13,LEN(A4)=9),"Valid Format","Invalid Format") -> Valid Format | AJ4: =IF(LEFT(C4,LEN(Settings!$B$14))=Settings!$B$14,"Valid Format","Invalid Format") -> Valid Format | AK4: =IF(COUNTIF(Master_Data!$G$5:$G$14,C4)=1,"Known Customer","Customer Not in Master") -> Customer Not in Master | AL4: =IF(U4>=Settings!$B$11,"Target Met","Below Target") -> Target Met | AM4: =IF(YEAR(B4)=Settings!$B$5,"Correct Year","Wrong Year") -> Correct Year | AN4: =COUNTIF(AI4:AM4,"*Valid*")+COUNTIF(AI4:AM4,"Known Customer")+COUNTIF(AI4:AM4,"Target Met")+COUNTIF(AI4:AM4,"Correct Year") -> 4
A5: =Raw_Data!A5 -> ORD-10004 | B5: =Raw_Data!B5 -> 45737 | C5: =Raw_Data!C5 -> C1012 | D5: =Raw_Data!D5 -> client98@example.com | E5: =Raw_Data!E5 -> P1005 | F5: =Raw_Data!F5 -> 24-inch Monitor | G5: =Raw_Data!G5 -> Electronics | H5: =Raw_Data!H5 -> Bucharest | ... P5: =Raw_Data!P5 -> Completed | Q5: =K5*L5 -> 2880 | R5: =Q5*(1-N5) -> 2736 | S5: =K5*M5 -> 2040 | T5: =R5-S5 -> 696 | U5: =IFERROR(T5/R5,0) -> 0.25438596 | V5: =IF(OR(A5="",COUNTIF($A$2:$A$301,A5)>1,C5="",D5="",ISERROR(SEARCH("@",D5)),ISERROR(SEARCH(".",D5)),COUNTIF(Lookups!$A$2:$A$11,E5)=0,F5="",H5="",K5<=0,L5<0,M5<0,N5<0,N5>0.5,COUNTIF(Lookups!$K$2:$K$4,P5)=0),"ERROR","VALID") -> VALID | W5: =IF(A5="","Missing Order ID; ","")&IF(COUNTIF($A$2:$A$301,A5)>1,"Duplicate Order ID; ","")&IF(C5="","Missing Customer ID; ","")&IF(OR(D5="",ISERROR(SEARCH("@",D5)),ISERROR(SEARCH(".",D5))),"Invalid Email; ","")&IF(COUNTIF(Lookups!$A$2:$A$11,E5)=0,"Unknown Product; ","")&IF(F5="","Missing Product Name; ","")&IF(H5="","Missing Region; ","")&IF(K5<=0,"Invalid Quantity; ","")&IF(L5<0,"Invalid Price; ","")&IF(M5<0,"Invalid Cost; ","")&IF(OR(N5<0,N5>0.5),"Invalid Discount; ","")&IF(COUNTIF(Lookups!$K$2:$K$4,P5)=0,"Invalid Status; ","") | X5: =TEXT(B5,"yyyy-mm") -> 2025-03 | Y5: ="Q"&ROUNDUP(MONTH(B5)/3,0) -> Q1 | Z5: =IF(R5>=Settings!$B$9,"High Value Customer",IF(R5>=Settings!$B$10,"Medium Value Customer","Standard Customer")) -> Medium Value Customer | AA5: =IF(R5>=Settings!$B$9,"Large Order",IF(R5>=Settings!$B$10,"Medium Order","Small Order")) -> Medium Order | AB5: =IF(N5=0,"No Discount",IF(N5<=0.1,"Low Discount",IF(N5<=Settings!$B$8,"Medium Discount","High Discount"))) -> Low Discount | AC5: =IF(T5>0,"Profitable",IF(T5=0,"Break-even","Loss")) -> Profitable | AD5: =IFERROR(VLOOKUP(E5,Lookups!$A$2:$E$11,2,FALSE),"Product Not Found") -> 24-inch Monitor | AE5: =IFERROR(VLOOKUP(E5,Lookups!$A$2:$E$11,3,FALSE),"Category Not Found") -> Electronics | AF5: =IFERROR(IF(L5=VLOOKUP(E5,Lookups!$A$2:$E$11,4,FALSE),"Price OK","Price Mismatch"),"Product Missing") -> Price OK | AG5: =IF(AND(ISNUMBER(SEARCH("@",D5)),ISNUMBER(SEARCH(".",D5))),"Valid Email","Invalid Email") -> Valid Email | AH5: =IF(AND(V5="VALID",AF5="Price OK",AG5="Valid Email"),"READY FOR REPORTING","REVIEW REQUIRED") -> READY FOR REPORTING | AI5: =IF(AND(LEFT(A5,LEN(Settings!$B$13))=Settings!$B$13,LEN(A5)=9),"Valid Format","Invalid Format") -> Valid Format | AJ5: =IF(LEFT(C5,LEN(Settings!$B$14))=Settings!$B$14,"Valid Format","Invalid Format") -> Valid Format | AK5: =IF(COUNTIF(Master_Data!$G$5:$G$14,C5)=1,"Known Customer","Customer Not in Master") -> Customer Not in Master | AL5: =IF(U5>=Settings!$B$11,"Target Met","Below Target") -> Target Met | AM5: =IF(YEAR(B5)=Settings!$B$5,"Correct Year","Wrong Year") -> Correct Year | AN5: =COUNTIF(AI5:AM5,"*Valid*")+COUNTIF(AI5:AM5,"Known Customer")+COUNTIF(AI5:AM5,"Target Met")+COUNTIF(AI5:AM5,"Correct Year") -> 4
A6: =Raw_Data!A6 -> ORD-10005 | B6: =Raw_Data!B6 -> 45893 | C6: =Raw_Data!C6 -> C1011 | D6: =Raw_Data!D6 -> client142@example.com | E6: =Raw_Data!E6 -> P1001 | F6: =Raw_Data!F6 -> Laptop Stand | G6: =Raw_Data!G6 -> Accessories | H6: =Raw_Data!H6 -> South | ... P6: =Raw_Data!P6 -> Completed | Q6: =K6*L6 -> 855 | R6: =Q6*(1-N6) -> 855 | S6: =K6*M6 -> 468 | T6: =R6-S6 -> 387 | U6: =IFERROR(T6/R6,0) -> 0.45263158 | V6: =IF(OR(A6="",COUNTIF($A$2:$A$301,A6)>1,C6="",D6="",ISERROR(SEARCH("@",D6)),ISERROR(SEARCH(".",D6)),COUNTIF(Lookups!$A$2:$A$11,E6)=0,F6="",H6="",K6<=0,L6<0,M6<0,N6<0,N6>0.5,COUNTIF(Lookups!$K$2:$K$4,P6)=0),"ERROR","VALID") -> VALID | W6: =IF(A6="","Missing Order ID; ","")&IF(COUNTIF($A$2:$A$301,A6)>1,"Duplicate Order ID; ","")&IF(C6="","Missing Customer ID; ","")&IF(OR(D6="",ISERROR(SEARCH("@",D6)),ISERROR(SEARCH(".",D6))),"Invalid Email; ","")&IF(COUNTIF(Lookups!$A$2:$A$11,E6)=0,"Unknown Product; ","")&IF(F6="","Missing Product Name; ","")&IF(H6="","Missing Region; ","")&IF(K6<=0,"Invalid Quantity; ","")&IF(L6<0,"Invalid Price; ","")&IF(M6<0,"Invalid Cost; ","")&IF(OR(N6<0,N6>0.5),"Invalid Discount; ","")&IF(COUNTIF(Lookups!$K$2:$K$4,P6)=0,"Invalid Status; ","") | X6: =TEXT(B6,"yyyy-mm") -> 2025-08 | Y6: ="Q"&ROUNDUP(MONTH(B6)/3,0) -> Q3 | Z6: =IF(R6>=Settings!$B$9,"High Value Customer",IF(R6>=Settings!$B$10,"Medium Value Customer","Standard Customer")) -> Standard Customer | AA6: =IF(R6>=Settings!$B$9,"Large Order",IF(R6>=Settings!$B$10,"Medium Order","Small Order")) -> Small Order | AB6: =IF(N6=0,"No Discount",IF(N6<=0.1,"Low Discount",IF(N6<=Settings!$B$8,"Medium Discount","High Discount"))) -> No Discount | AC6: =IF(T6>0,"Profitable",IF(T6=0,"Break-even","Loss")) -> Profitable | AD6: =IFERROR(VLOOKUP(E6,Lookups!$A$2:$E$11,2,FALSE),"Product Not Found") -> Laptop Stand | AE6: =IFERROR(VLOOKUP(E6,Lookups!$A$2:$E$11,3,FALSE),"Category Not Found") -> Accessories | AF6: =IFERROR(IF(L6=VLOOKUP(E6,Lookups!$A$2:$E$11,4,FALSE),"Price OK","Price Mismatch"),"Product Missing") -> Price OK | AG6: =IF(AND(ISNUMBER(SEARCH("@",D6)),ISNUMBER(SEARCH(".",D6))),"Valid Email","Invalid Email") -> Valid Email | AH6: =IF(AND(V6="VALID",AF6="Price OK",AG6="Valid Email"),"READY FOR REPORTING","REVIEW REQUIRED") -> READY FOR REPORTING | AI6: =IF(AND(LEFT(A6,LEN(Settings!$B$13))=Settings!$B$13,LEN(A6)=9),"Valid Format","Invalid Format") -> Valid Format | AJ6: =IF(LEFT(C6,LEN(Settings!$B$14))=Settings!$B$14,"Valid Format","Invalid Format") -> Valid Format | AK6: =IF(COUNTIF(Master_Data!$G$5:$G$14,C6)=1,"Known Customer","Customer Not in Master") -> Customer Not in Master | AL6: =IF(U6>=Settings!$B$11,"Target Met","Below Target") -> Target Met | AM6: =IF(YEAR(B6)=Settings!$B$5,"Correct Year","Wrong Year") -> Correct Year | AN6: =COUNTIF(AI6:AM6,"*Valid*")+COUNTIF(AI6:AM6,"Known Customer")+COUNTIF(AI6:AM6,"Target Met")+COUNTIF(AI6:AM6,"Correct Year") -> 4
A7: =Raw_Data!A7 -> ORD-10006 | B7: =Raw_Data!B7 -> 45756 | C7: =Raw_Data!C7 -> C1085 | D7: =Raw_Data!D7 -> client59@example.com | E7: =Raw_Data!E7 -> P1010 | F7: =Raw_Data!F7 -> Headset | G7: =Raw_Data!G7 -> Electronics | H7: =Raw_Data!H7 -> South | ... P7: =Raw_Data!P7 -> Completed | Q7: =K7*L7 -> 2340 | R7: =Q7*(1-N7) -> 2340 | S7: =K7*M7 -> 1260 | T7: =R7-S7 -> 1080 | U7: =IFERROR(T7/R7,0) -> 0.46153846 | V7: =IF(OR(A7="",COUNTIF($A$2:$A$301,A7)>1,C7="",D7="",ISERROR(SEARCH("@",D7)),ISERROR(SEARCH(".",D7)),COUNTIF(Lookups!$A$2:$A$11,E7)=0,F7="",H7="",K7<=0,L7<0,M7<0,N7<0,N7>0.5,COUNTIF(Lookups!$K$2:$K$4,P7)=0),"ERROR","VALID") -> VALID | W7: =IF(A7="","Missing Order ID; ","")&IF(COUNTIF($A$2:$A$301,A7)>1,"Duplicate Order ID; ","")&IF(C7="","Missing Customer ID; ","")&IF(OR(D7="",ISERROR(SEARCH("@",D7)),ISERROR(SEARCH(".",D7))),"Invalid Email; ","")&IF(COUNTIF(Lookups!$A$2:$A$11,E7)=0,"Unknown Product; ","")&IF(F7="","Missing Product Name; ","")&IF(H7="","Missing Region; ","")&IF(K7<=0,"Invalid Quantity; ","")&IF(L7<0,"Invalid Price; ","")&IF(M7<0,"Invalid Cost; ","")&IF(OR(N7<0,N7>0.5),"Invalid Discount; ","")&IF(COUNTIF(Lookups!$K$2:$K$4,P7)=0,"Invalid Status; ","") | X7: =TEXT(B7,"yyyy-mm") -> 2025-04 | Y7: ="Q"&ROUNDUP(MONTH(B7)/3,0) -> Q2 | Z7: =IF(R7>=Settings!$B$9,"High Value Customer",IF(R7>=Settings!$B$10,"Medium Value Customer","Standard Customer")) -> Medium Value Customer | AA7: =IF(R7>=Settings!$B$9,"Large Order",IF(R7>=Settings!$B$10,"Medium Order","Small Order")) -> Medium Order | AB7: =IF(N7=0,"No Discount",IF(N7<=0.1,"Low Discount",IF(N7<=Settings!$B$8,"Medium Discount","High Discount"))) -> No Discount | AC7: =IF(T7>0,"Profitable",IF(T7=0,"Break-even","Loss")) -> Profitable | AD7: =IFERROR(VLOOKUP(E7,Lookups!$A$2:$E$11,2,FALSE),"Product Not Found") -> Headset | AE7: =IFERROR(VLOOKUP(E7,Lookups!$A$2:$E$11,3,FALSE),"Category Not Found") -> Electronics | AF7: =IFERROR(IF(L7=VLOOKUP(E7,Lookups!$A$2:$E$11,4,FALSE),"Price OK","Price Mismatch"),"Product Missing") -> Price OK | AG7: =IF(AND(ISNUMBER(SEARCH("@",D7)),ISNUMBER(SEARCH(".",D7))),"Valid Email","Invalid Email") -> Valid Email | AH7: =IF(AND(V7="VALID",AF7="Price OK",AG7="Valid Email"),"READY FOR REPORTING","REVIEW REQUIRED") -> READY FOR REPORTING | AI7: =IF(AND(LEFT(A7,LEN(Settings!$B$13))=Settings!$B$13,LEN(A7)=9),"Valid Format","Invalid Format") -> Valid Format | AJ7: =IF(LEFT(C7,LEN(Settings!$B$14))=Settings!$B$14,"Valid Format","Invalid Format") -> Valid Format | AK7: =IF(COUNTIF(Master_Data!$G$5:$G$14,C7)=1,"Known Customer","Customer Not in Master") -> Customer Not in Master | AL7: =IF(U7>=Settings!$B$11,"Target Met","Below Target") -> Target Met | AM7: =IF(YEAR(B7)=Settings!$B$5,"Correct Year","Wrong Year") -> Correct Year | AN7: =COUNTIF(AI7:AM7,"*Valid*")+COUNTIF(AI7:AM7,"Known Customer")+COUNTIF(AI7:AM7,"Target Met")+COUNTIF(AI7:AM7,"Correct Year") -> 4
A8: =Raw_Data!A8 -> ORD-10007 | B8: =Raw_Data!B8 -> 45800 | C8: =Raw_Data!C8 -> C1021 | D8: =Raw_Data!D8 -> client95@example.com | E8: =Raw_Data!E8 -> P1007 | F8: =Raw_Data!F8 -> Office Chair | G8: =Raw_Data!G8 -> Furniture | H8: =Raw_Data!H8 -> South | ... P8: =Raw_Data!P8 -> Completed | Q8: =K8*L8 -> 6720 | R8: =Q8*(1-N8) -> 5376 | S8: =K8*M8 -> 4720 | T8: =R8-S8 -> 656 | U8: =IFERROR(T8/R8,0) -> 0.12202381 | V8: =IF(OR(A8="",COUNTIF($A$2:$A$301,A8)>1,C8="",D8="",ISERROR(SEARCH("@",D8)),ISERROR(SEARCH(".",D8)),COUNTIF(Lookups!$A$2:$A$11,E8)=0,F8="",H8="",K8<=0,L8<0,M8<0,N8<0,N8>0.5,COUNTIF(Lookups!$K$2:$K$4,P8)=0),"ERROR","VALID") -> VALID | W8: =IF(A8="","Missing Order ID; ","")&IF(COUNTIF($A$2:$A$301,A8)>1,"Duplicate Order ID; ","")&IF(C8="","Missing Customer ID; ","")&IF(OR(D8="",ISERROR(SEARCH("@",D8)),ISERROR(SEARCH(".",D8))),"Invalid Email; ","")&IF(COUNTIF(Lookups!$A$2:$A$11,E8)=0,"Unknown Product; ","")&IF(F8="","Missing Product Name; ","")&IF(H8="","Missing Region; ","")&IF(K8<=0,"Invalid Quantity; ","")&IF(L8<0,"Invalid Price; ","")&IF(M8<0,"Invalid Cost; ","")&IF(OR(N8<0,N8>0.5),"Invalid Discount; ","")&IF(COUNTIF(Lookups!$K$2:$K$4,P8)=0,"Invalid Status; ","") | X8: =TEXT(B8,"yyyy-mm") -> 2025-05 | Y8: ="Q"&ROUNDUP(MONTH(B8)/3,0) -> Q2 | Z8: =IF(R8>=Settings!$B$9,"High Value Customer",IF(R8>=Settings!$B$10,"Medium Value Customer","Standard Customer")) -> High Value Customer | AA8: =IF(R8>=Settings!$B$9,"Large Order",IF(R8>=Settings!$B$10,"Medium Order","Small Order")) -> Large Order | AB8: =IF(N8=0,"No Discount",IF(N8<=0.1,"Low Discount",IF(N8<=Settings!$B$8,"Medium Discount","High Discount"))) -> Medium Discount | AC8: =IF(T8>0,"Profitable",IF(T8=0,"Break-even","Loss")) -> Profitable | AD8: =IFERROR(VLOOKUP(E8,Lookups!$A$2:$E$11,2,FALSE),"Product Not Found") -> Office Chair | AE8: =IFERROR(VLOOKUP(E8,Lookups!$A$2:$E$11,3,FALSE),"Category Not Found") -> Furniture | AF8: =IFERROR(IF(L8=VLOOKUP(E8,Lookups!$A$2:$E$11,4,FALSE),"Price OK","Price Mismatch"),"Product Missing") -> Price OK | AG8: =IF(AND(ISNUMBER(SEARCH("@",D8)),ISNUMBER(SEARCH(".",D8))),"Valid Email","Invalid Email") -> Valid Email | AH8: =IF(AND(V8="VALID",AF8="Price OK",AG8="Valid Email"),"READY FOR REPORTING","REVIEW REQUIRED") -> READY FOR REPORTING | AI8: =IF(AND(LEFT(A8,LEN(Settings!$B$13))=Settings!$B$13,LEN(A8)=9),"Valid Format","Invalid Format") -> Valid Format | AJ8: =IF(LEFT(C8,LEN(Settings!$B$14))=Settings!$B$14,"Valid Format","Invalid Format") -> Valid Format | AK8: =IF(COUNTIF(Master_Data!$G$5:$G$14,C8)=1,"Known Customer","Customer Not in Master") -> Customer Not in Master | AL8: =IF(U8>=Settings!$B$11,"Target Met","Below Target") -> Below Target | AM8: =IF(YEAR(B8)=Settings!$B$5,"Correct Year","Wrong Year") -> Correct Year | AN8: =COUNTIF(AI8:AM8,"*Valid*")+COUNTIF(AI8:AM8,"Known Customer")+COUNTIF(AI8:AM8,"Target Met")+COUNTIF(AI8:AM8,"Correct Year") -> 3
A9: =Raw_Data!A9 -> ORD-10008 | B9: =Raw_Data!B9 -> 45983 | C9: =Raw_Data!C9 -> C1032 | D9: =Raw_Data!D9 -> client42@example.com | E9: =Raw_Data!E9 -> P1010 | F9: =Raw_Data!F9 -> Headset | G9: =Raw_Data!G9 -> Electronics | H9: =Raw_Data!H9 -> East | ... P9: =Raw_Data!P9 -> Cancelled | Q9: =K9*L9 -> 585 | R9: =Q9*(1-N9) -> 497.25 | S9: =K9*M9 -> 315 | T9: =R9-S9 -> 182.25 | U9: =IFERROR(T9/R9,0) -> 0.36651584 | V9: =IF(OR(A9="",COUNTIF($A$2:$A$301,A9)>1,C9="",D9="",ISERROR(SEARCH("@",D9)),ISERROR(SEARCH(".",D9)),COUNTIF(Lookups!$A$2:$A$11,E9)=0,F9="",H9="",K9<=0,L9<0,M9<0,N9<0,N9>0.5,COUNTIF(Lookups!$K$2:$K$4,P9)=0),"ERROR","VALID") -> VALID | W9: =IF(A9="","Missing Order ID; ","")&IF(COUNTIF($A$2:$A$301,A9)>1,"Duplicate Order ID; ","")&IF(C9="","Missing Customer ID; ","")&IF(OR(D9="",ISERROR(SEARCH("@",D9)),ISERROR(SEARCH(".",D9))),"Invalid Email; ","")&IF(COUNTIF(Lookups!$A$2:$A$11,E9)=0,"Unknown Product; ","")&IF(F9="","Missing Product Name; ","")&IF(H9="","Missing Region; ","")&IF(K9<=0,"Invalid Quantity; ","")&IF(L9<0,"Invalid Price; ","")&IF(M9<0,"Invalid Cost; ","")&IF(OR(N9<0,N9>0.5),"Invalid Discount; ","")&IF(COUNTIF(Lookups!$K$2:$K$4,P9)=0,"Invalid Status; ","") | X9: =TEXT(B9,"yyyy-mm") -> 2025-11 | Y9: ="Q"&ROUNDUP(MONTH(B9)/3,0) -> Q4 | Z9: =IF(R9>=Settings!$B$9,"High Value Customer",IF(R9>=Settings!$B$10,"Medium Value Customer","Standard Customer")) -> Standard Customer | AA9: =IF(R9>=Settings!$B$9,"Large Order",IF(R9>=Settings!$B$10,"Medium Order","Small Order")) -> Small Order | AB9: =IF(N9=0,"No Discount",IF(N9<=0.1,"Low Discount",IF(N9<=Settings!$B$8,"Medium Discount","High Discount"))) -> Medium Discount | AC9: =IF(T9>0,"Profitable",IF(T9=0,"Break-even","Loss")) -> Profitable | AD9: =IFERROR(VLOOKUP(E9,Lookups!$A$2:$E$11,2,FALSE),"Product Not Found") -> Headset | AE9: =IFERROR(VLOOKUP(E9,Lookups!$A$2:$E$11,3,FALSE),"Category Not Found") -> Electronics | AF9: =IFERROR(IF(L9=VLOOKUP(E9,Lookups!$A$2:$E$11,4,FALSE),"Price OK","Price Mismatch"),"Product Missing") -> Price OK | AG9: =IF(AND(ISNUMBER(SEARCH("@",D9)),ISNUMBER(SEARCH(".",D9))),"Valid Email","Invalid Email") -> Valid Email | AH9: =IF(AND(V9="VALID",AF9="Price OK",AG9="Valid Email"),"READY FOR REPORTING","REVIEW REQUIRED") -> READY FOR REPORTING | AI9: =IF(AND(LEFT(A9,LEN(Settings!$B$13))=Settings!$B$13,LEN(A9)=9),"Valid Format","Invalid Format") -> Valid Format | AJ9: =IF(LEFT(C9,LEN(Settings!$B$14))=Settings!$B$14,"Valid Format","Invalid Format") -> Valid Format | AK9: =IF(COUNTIF(Master_Data!$G$5:$G$14,C9)=1,"Known Customer","Customer Not in Master") -> Customer Not in Master | AL9: =IF(U9>=Settings!$B$11,"Target Met","Below Target") -> Target Met | AM9: =IF(YEAR(B9)=Settings!$B$5,"Correct Year","Wrong Year") -> Correct Year | AN9: =COUNTIF(AI9:AM9,"*Valid*")+COUNTIF(AI9:AM9,"Known Customer")+COUNTIF(AI9:AM9,"Target Met")+COUNTIF(AI9:AM9,"Correct Year") -> 4
A10: =Raw_Data!A10 -> ORD-10009 | B10: =Raw_Data!B10 -> 45686 | C10: =Raw_Data!C10 -> C1052 | D10: =Raw_Data!D10 -> client69@example.com | E10: =Raw_Data!E10 -> P1006 | F10: =Raw_Data!F10 -> 27-inch Monitor | G10: =Raw_Data!G10 -> Electronics | H10: =Raw_Data!H10 -> Bucharest | ... P10: =Raw_Data!P10 -> Completed | Q10: =K10*L10 -> 4360 | R10: =Q10*(1-N10) -> 4360 | S10: =K10*M10 -> 3160 | T10: =R10-S10 -> 1200 | U10: =IFERROR(T10/R10,0) -> 0.27522936 | V10: =IF(OR(A10="",COUNTIF($A$2:$A$301,A10)>1,C10="",D10="",ISERROR(SEARCH("@",D10)),ISERROR(SEARCH(".",D10)),COUNTIF(Lookups!$A$2:$A$11,E10)=0,F10="",H10="",K10<=0,L10<0,M10<0,N10<0,N10>0.5,COUNTIF(Lookups!$K$2:$K$4,P10)=0),"ERROR","VALID") -> VALID | W10: =IF(A10="","Missing Order ID; ","")&IF(COUNTIF($A$2:$A$301,A10)>1,"Duplicate Order ID; ","")&IF(C10="","Missing Customer ID; ","")&IF(OR(D10="",ISERROR(SEARCH("@",D10)),ISERROR(SEARCH(".",D10))),"Invalid Email; ","")&IF(COUNTIF(Lookups!$A$2:$A$11,E10)=0,"Unknown Product; ","")&IF(F10="","Missing Product Name; ","")&IF(H10="","Missing Region; ","")&IF(K10<=0,"Invalid Quantity; ","")&IF(L10<0,"Invalid Price; ","")&IF(M10<0,"Invalid Cost; ","")&IF(OR(N10<0,N10>0.5),"Invalid Discount; ","")&IF(COUNTIF(Lookups!$K$2:$K$4,P10)=0,"Invalid Status; ","") | X10: =TEXT(B10,"yyyy-mm") -> 2025-01 | Y10: ="Q"&ROUNDUP(MONTH(B10)/3,0) -> Q1 | Z10: =IF(R10>=Settings!$B$9,"High Value Customer",IF(R10>=Settings!$B$10,"Medium Value Customer","Standard Customer")) -> Medium Value Customer | AA10: =IF(R10>=Settings!$B$9,"Large Order",IF(R10>=Settings!$B$10,"Medium Order","Small Order")) -> Medium Order | AB10: =IF(N10=0,"No Discount",IF(N10<=0.1,"Low Discount",IF(N10<=Settings!$B$8,"Medium Discount","High Discount"))) -> No Discount | AC10: =IF(T10>0,"Profitable",IF(T10=0,"Break-even","Loss")) -> Profitable | AD10: =IFERROR(VLOOKUP(E10,Lookups!$A$2:$E$11,2,FALSE),"Product Not Found") -> 27-inch Monitor | AE10: =IFERROR(VLOOKUP(E10,Lookups!$A$2:$E$11,3,FALSE),"Category Not Found") -> Electronics | AF10: =IFERROR(IF(L10=VLOOKUP(E10,Lookups!$A$2:$E$11,4,FALSE),"Price OK","Price Mismatch"),"Product Missing") -> Price OK | AG10: =IF(AND(ISNUMBER(SEARCH("@",D10)),ISNUMBER(SEARCH(".",D10))),"Valid Email","Invalid Email") -> Valid Email | AH10: =IF(AND(V10="VALID",AF10="Price OK",AG10="Valid Email"),"READY FOR REPORTING","REVIEW REQUIRED") -> READY FOR REPORTING | AI10: =IF(AND(LEFT(A10,LEN(Settings!$B$13))=Settings!$B$13,LEN(A10)=9),"Valid Format","Invalid Format") -> Valid Format | AJ10: =IF(LEFT(C10,LEN(Settings!$B$14))=Settings!$B$14,"Valid Format","Invalid Format") -> Valid Format | AK10: =IF(COUNTIF(Master_Data!$G$5:$G$14,C10)=1,"Known Customer","Customer Not in Master") -> Customer Not in Master | AL10: =IF(U10>=Settings!$B$11,"Target Met","Below Target") -> Target Met | AM10: =IF(YEAR(B10)=Settings!$B$5,"Correct Year","Wrong Year") -> Correct Year | AN10: =COUNTIF(AI10:AM10,"*Valid*")+COUNTIF(AI10:AM10,"Known Customer")+COUNTIF(AI10:AM10,"Target Met")+COUNTIF(AI10:AM10,"Correct Year") -> 4
A11: =Raw_Data!A11 -> ORD-10010 | B11: =Raw_Data!B11 -> 45993 | C11: =Raw_Data!C11 -> C1059 | D11: =Raw_Data!D11 -> invalid-email | E11: =Raw_Data!E11 -> P1004 | F11: =Raw_Data!F11 -> USB-C Hub | G11: =Raw_Data!G11 -> Accessories | H11: =Raw_Data!H11 -> South | ... P11: =Raw_Data!P11 -> Cancelled | Q11: =K11*L11 -> 1400 | R11: =Q11*(1-N11) -> 1260 | S11: =K11*M11 -> 784 | T11: =R11-S11 -> 476 | U11: =IFERROR(T11/R11,0) -> 0.37777778 | V11: =IF(OR(A11="",COUNTIF($A$2:$A$301,A11)>1,C11="",D11="",ISERROR(SEARCH("@",D11)),ISERROR(SEARCH(".",D11)),COUNTIF(Lookups!$A$2:$A$11,E11)=0,F11="",H11="",K11<=0,L11<0,M11<0,N11<0,N11>0.5,COUNTIF(Lookups!$K$2:$K$4,P11)=0),"ERROR","VALID") -> ERROR | W11: =IF(A11="","Missing Order ID; ","")&IF(COUNTIF($A$2:$A$301,A11)>1,"Duplicate Order ID; ","")&IF(C11="","Missing Customer ID; ","")&IF(OR(D11="",ISERROR(SEARCH("@",D11)),ISERROR(SEARCH(".",D11))),"Invalid Email; ","")&IF(COUNTIF(Lookups!$A$2:$A$11,E11)=0,"Unknown Product; ","")&IF(F11="","Missing Product Name; ","")&IF(H11="","Missing Region; ","")&IF(K11<=0,"Invalid Quantity; ","")&IF(L11<0,"Invalid Price; ","")&IF(M11<0,"Invalid Cost; ","")&IF(OR(N11<0,N11>0.5),"Invalid Discount; ","")&IF(COUNTIF(Lookups!$K$2:$K$4,P11)=0,"Invalid Status; ","") -> Invalid Email; | X11: =TEXT(B11,"yyyy-mm") -> 2025-12 | Y11: ="Q"&ROUNDUP(MONTH(B11)/3,0) -> Q4 | Z11: =IF(R11>=Settings!$B$9,"High Value Customer",IF(R11>=Settings!$B$10,"Medium Value Customer","Standard Customer")) -> Standard Customer | AA11: =IF(R11>=Settings!$B$9,"Large Order",IF(R11>=Settings!$B$10,"Medium Order","Small Order")) -> Small Order | AB11: =IF(N11=0,"No Discount",IF(N11<=0.1,"Low Discount",IF(N11<=Settings!$B$8,"Medium Discount","High Discount"))) -> Low Discount | AC11: =IF(T11>0,"Profitable",IF(T11=0,"Break-even","Loss")) -> Profitable | AD11: =IFERROR(VLOOKUP(E11,Lookups!$A$2:$E$11,2,FALSE),"Product Not Found") -> USB-C Hub | AE11: =IFERROR(VLOOKUP(E11,Lookups!$A$2:$E$11,3,FALSE),"Category Not Found") -> Accessories | AF11: =IFERROR(IF(L11=VLOOKUP(E11,Lookups!$A$2:$E$11,4,FALSE),"Price OK","Price Mismatch"),"Product Missing") -> Price OK | AG11: =IF(AND(ISNUMBER(SEARCH("@",D11)),ISNUMBER(SEARCH(".",D11))),"Valid Email","Invalid Email") -> Invalid Email | AH11: =IF(AND(V11="VALID",AF11="Price OK",AG11="Valid Email"),"READY FOR REPORTING","REVIEW REQUIRED") -> REVIEW REQUIRED | AI11: =IF(AND(LEFT(A11,LEN(Settings!$B$13))=Settings!$B$13,LEN(A11)=9),"Valid Format","Invalid Format") -> Valid Format | AJ11: =IF(LEFT(C11,LEN(Settings!$B$14))=Settings!$B$14,"Valid Format","Invalid Format") -> Valid Format | AK11: =IF(COUNTIF(Master_Data!$G$5:$G$14,C11)=1,"Known Customer","Customer Not in Master") -> Customer Not in Master | AL11: =IF(U11>=Settings!$B$11,"Target Met","Below Target") -> Target Met | AM11: =IF(YEAR(B11)=Settings!$B$5,"Correct Year","Wrong Year") -> Correct Year | AN11: =COUNTIF(AI11:AM11,"*Valid*")+COUNTIF(AI11:AM11,"Known Customer")+COUNTIF(AI11:AM11,"Target Met")+COUNTIF(AI11:AM11,"Correct Year") -> 4
A12: =Raw_Data!A12 -> ORD-10011 | B12: =Raw_Data!B12 -> 45877 | C12: =Raw_Data!C12 -> C1029 | D12: =Raw_Data!D12 -> client36@example.com | E12: =Raw_Data!E12 -> P1010 | F12: =Raw_Data!F12 -> Headset | G12: =Raw_Data!G12 -> Electronics | H12: =Raw_Data!H12 -> West | ... P12: =Raw_Data!P12 -> Completed | Q12: =K12*L12 -> 1950 | R12: =Q12*(1-N12) -> 1755 | S12: =K12*M12 -> 1050 | T12: =R12-S12 -> 705 | U12: =IFERROR(T12/R12,0) -> 0.4017094 | V12: =IF(OR(A12="",COUNTIF($A$2:$A$301,A12)>1,C12="",D12="",ISERROR(SEARCH("@",D12)),ISERROR(SEARCH(".",D12)),COUNTIF(Lookups!$A$2:$A$11,E12)=0,F12="",H12="",K12<=0,L12<0,M12<0,N12<0,N12>0.5,COUNTIF(Lookups!$K$2:$K$4,P12)=0),"ERROR","VALID") -> VALID | W12: =IF(A12="","Missing Order ID; ","")&IF(COUNTIF($A$2:$A$301,A12)>1,"Duplicate Order ID; ","")&IF(C12="","Missing Customer ID; ","")&IF(OR(D12="",ISERROR(SEARCH("@",D12)),ISERROR(SEARCH(".",D12))),"Invalid Email; ","")&IF(COUNTIF(Lookups!$A$2:$A$11,E12)=0,"Unknown Product; ","")&IF(F12="","Missing Product Name; ","")&IF(H12="","Missing Region; ","")&IF(K12<=0,"Invalid Quantity; ","")&IF(L12<0,"Invalid Price; ","")&IF(M12<0,"Invalid Cost; ","")&IF(OR(N12<0,N12>0.5),"Invalid Discount; ","")&IF(COUNTIF(Lookups!$K$2:$K$4,P12)=0,"Invalid Status; ","") | X12: =TEXT(B12,"yyyy-mm") -> 2025-08 | Y12: ="Q"&ROUNDUP(MONTH(B12)/3,0) -> Q3 | Z12: =IF(R12>=Settings!$B$9,"High Value Customer",IF(R12>=Settings!$B$10,"Medium Value Customer","Standard Customer")) -> Standard Customer | AA12: =IF(R12>=Settings!$B$9,"Large Order",IF(R12>=Settings!$B$10,"Medium Order","Small Order")) -> Small Order | AB12: =IF(N12=0,"No Discount",IF(N12<=0.1,"Low Discount",IF(N12<=Settings!$B$8,"Medium Discount","High Discount"))) -> Low Discount | AC12: =IF(T12>0,"Profitable",IF(T12=0,"Break-even","Loss")) -> Profitable | AD12: =IFERROR(VLOOKUP(E12,Lookups!$A$2:$E$11,2,FALSE),"Product Not Found") -> Headset | AE12: =IFERROR(VLOOKUP(E12,Lookups!$A$2:$E$11,3,FALSE),"Category Not Found") -> Electronics | AF12: =IFERROR(IF(L12=VLOOKUP(E12,Lookups!$A$2:$E$11,4,FALSE),"Price OK","Price Mismatch"),"Product Missing") -> Price OK | AG12: =IF(AND(ISNUMBER(SEARCH("@",D12)),ISNUMBER(SEARCH(".",D12))),"Valid Email","Invalid Email") -> Valid Email | AH12: =IF(AND(V12="VALID",AF12="Price OK",AG12="Valid Email"),"READY FOR REPORTING","REVIEW REQUIRED") -> READY FOR REPORTING | AI12: =IF(AND(LEFT(A12,LEN(Settings!$B$13))=Settings!$B$13,LEN(A12)=9),"Valid Format","Invalid Format") -> Valid Format | AJ12: =IF(LEFT(C12,LEN(Settings!$B$14))=Settings!$B$14,"Valid Format","Invalid Format") -> Valid Format | AK12: =IF(COUNTIF(Master_Data!$G$5:$G$14,C12)=1,"Known Customer","Customer Not in Master") -> Customer Not in Master | AL12: =IF(U12>=Settings!$B$11,"Target Met","Below Target") -> Target Met | AM12: =IF(YEAR(B12)=Settings!$B$5,"Correct Year","Wrong Year") -> Correct Year | AN12: =COUNTIF(AI12:AM12,"*Valid*")+COUNTIF(AI12:AM12,"Known Customer")+COUNTIF(AI12:AM12,"Target Met")+COUNTIF(AI12:AM12,"Correct Year") -> 4
A13: =Raw_Data!A13 -> ORD-10012 | B13: =Raw_Data!B13 -> 45736 | C13: =Raw_Data!C13 -> C1055 | D13: =Raw_Data!D13 -> client153@example.com | E13: =Raw_Data!E13 -> P1002 | F13: =Raw_Data!F13 -> Wireless Mouse | G13: =Raw_Data!G13 -> Accessories | H13: =Raw_Data!H13 -> Bucharest | ... P13: =Raw_Data!P13 -> Cancelled | Q13: =K13*L13 -> 935 | R13: =Q13*(1-N13) -> 935 | S13: =K13*M13 -> 484 | T13: =R13-S13 -> 451 | U13: =IFERROR(T13/R13,0) -> 0.48235294 | V13: =IF(OR(A13="",COUNTIF($A$2:$A$301,A13)>1,C13="",D13="",ISERROR(SEARCH("@",D13)),ISERROR(SEARCH(".",D13)),COUNTIF(Lookups!$A$2:$A$11,E13)=0,F13="",H13="",K13<=0,L13<0,M13<0,N13<0,N13>0.5,COUNTIF(Lookups!$K$2:$K$4,P13)=0),"ERROR","VALID") -> VALID | W13: =IF(A13="","Missing Order ID; ","")&IF(COUNTIF($A$2:$A$301,A13)>1,"Duplicate Order ID; ","")&IF(C13="","Missing Customer ID; ","")&IF(OR(D13="",ISERROR(SEARCH("@",D13)),ISERROR(SEARCH(".",D13))),"Invalid Email; ","")&IF(COUNTIF(Lookups!$A$2:$A$11,E13)=0,"Unknown Product; ","")&IF(F13="","Missing Product Name; ","")&IF(H13="","Missing Region; ","")&IF(K13<=0,"Invalid Quantity; ","")&IF(L13<0,"Invalid Price; ","")&IF(M13<0,"Invalid Cost; ","")&IF(OR(N13<0,N13>0.5),"Invalid Discount; ","")&IF(COUNTIF(Lookups!$K$2:$K$4,P13)=0,"Invalid Status; ","") | X13: =TEXT(B13,"yyyy-mm") -> 2025-03 | Y13: ="Q"&ROUNDUP(MONTH(B13)/3,0) -> Q1 | Z13: =IF(R13>=Settings!$B$9,"High Value Customer",IF(R13>=Settings!$B$10,"Medium Value Customer","Standard Customer")) -> Standard Customer | AA13: =IF(R13>=Settings!$B$9,"Large Order",IF(R13>=Settings!$B$10,"Medium Order","Small Order")) -> Small Order | AB13: =IF(N13=0,"No Discount",IF(N13<=0.1,"Low Discount",IF(N13<=Settings!$B$8,"Medium Discount","High Discount"))) -> No Discount | AC13: =IF(T13>0,"Profitable",IF(T13=0,"Break-even","Loss")) -> Profitable | AD13: =IFERROR(VLOOKUP(E13,Lookups!$A$2:$E$11,2,FALSE),"Product Not Found") -> Wireless Mouse | AE13: =IFERROR(VLOOKUP(E13,Lookups!$A$2:$E$11,3,FALSE),"Category Not Found") -> Accessories | AF13: =IFERROR(IF(L13=VLOOKUP(E13,Lookups!$A$2:$E$11,4,FALSE),"Price OK","Price Mismatch"),"Product Missing") -> Price OK | AG13: =IF(AND(ISNUMBER(SEARCH("@",D13)),ISNUMBER(SEARCH(".",D13))),"Valid Email","Invalid Email") -> Valid Email | AH13: =IF(AND(V13="VALID",AF13="Price OK",AG13="Valid Email"),"READY FOR REPORTING","REVIEW REQUIRED") -> READY FOR REPORTING | AI13: =IF(AND(LEFT(A13,LEN(Settings!$B$13))=Settings!$B$13,LEN(A13)=9),"Valid Format","Invalid Format") -> Valid Format | AJ13: =IF(LEFT(C13,LEN(Settings!$B$14))=Settings!$B$14,"Valid Format","Invalid Format") -> Valid Format | AK13: =IF(COUNTIF(Master_Data!$G$5:$G$14,C13)=1,"Known Customer","Customer Not in Master") -> Customer Not in Master | AL13: =IF(U13>=Settings!$B$11,"Target Met","Below Target") -> Target Met | AM13: =IF(YEAR(B13)=Settings!$B$5,"Correct Year","Wrong Year") -> Correct Year | AN13: =COUNTIF(AI13:AM13,"*Valid*")+COUNTIF(AI13:AM13,"Known Customer")+COUNTIF(AI13:AM13,"Target Met")+COUNTIF(AI13:AM13,"Correct Year") -> 4
... A301: =Raw_Data!A301 -> ORD-10300 | B301: =Raw_Data!B301 -> 45824 | C301: =Raw_Data!C301 -> C1034 | D301: =Raw_Data!D301 -> client172@example.com | E301: =Raw_Data!E301 -> P1006 | F301: =Raw_Data!F301 -> 27-inch Monitor | G301: =Raw_Data!G301 -> Electronics | H301: =Raw_Data!H301 -> East | ... P301: =Raw_Data!P301 -> Completed | Q301: =K301*L301 -> 4360 | R301: =Q301*(1-N301) -> 3924 | S301: =K301*M301 -> 3160 | T301: =R301-S301 -> 764 | U301: =IFERROR(T301/R301,0) -> 0.19469929 | V301: =IF(OR(A301="",COUNTIF($A$2:$A$301,A301)>1,C301="",D301="",ISERROR(SEARCH("@",D301)),ISERROR(SEARCH(".",D301)),COUNTIF(Lookups!$A$2:$A$11,E301)=0,F301="",H301="",K301<=0,L301<0,M301<0,N301<0,N301>0.5,COUNTIF(Lookups!$K$2:$K$4,P301)=0),"ERROR","VALID") -> VALID | W301: =IF(A301="","Missing Order ID; ","")&IF(COUNTIF($A$2:$A$301,A301)>1,"Duplicate Order ID; ","")&IF(C301="","Missing Customer ID; ","")&IF(OR(D301="",ISERROR(SEARCH("@",D301)),ISERROR(SEARCH(".",D301))),"Invalid Email; ","")&IF(COUNTIF(Lookups!$A$2:$A$11,E301)=0,"Unknown Product; ","")&IF(F301="","Missing Product Name; ","")&IF(H301="","Missing Region; ","")&IF(K301<=0,"Invalid Quantity; ","")&IF(L301<0,"Invalid Price; ","")&IF(M301<0,"Invalid Cost; ","")&IF(OR(N301<0,N301>0.5),"Invalid Discount; ","")&IF(COUNTIF(Lookups!$K$2:$K$4,P301)=0,"Invalid Status; ","") | X301: =TEXT(B301,"yyyy-mm") -> 2025-06 | Y301: ="Q"&ROUNDUP(MONTH(B301)/3,0) -> Q2 | Z301: =IF(R301>=Settings!$B$9,"High Value Customer",IF(R301>=Settings!$B$10,"Medium Value Customer","Standard Customer")) -> Medium Value Customer | AA301: =IF(R301>=Settings!$B$9,"Large Order",IF(R301>=Settings!$B$10,"Medium Order","Small Order")) -> Medium Order | AB301: =IF(N301=0,"No Discount",IF(N301<=0.1,"Low Discount",IF(N301<=Settings!$B$8,"Medium Discount","High Discount"))) -> Low Discount | AC301: =IF(T301>0,"Profitable",IF(T301=0,"Break-even","Loss")) -> Profitable | AD301: =IFERROR(VLOOKUP(E301,Lookups!$A$2:$E$11,2,FALSE),"Product Not Found") -> 27-inch Monitor | AE301: =IFERROR(VLOOKUP(E301,Lookups!$A$2:$E$11,3,FALSE),"Category Not Found") -> Electronics | AF301: =IFERROR(IF(L301=VLOOKUP(E301,Lookups!$A$2:$E$11,4,FALSE),"Price OK","Price Mismatch"),"Product Missing") -> Price OK | AG301: =IF(AND(ISNUMBER(SEARCH("@",D301)),ISNUMBER(SEARCH(".",D301))),"Valid Email","Invalid Email") -> Valid Email | AH301: =IF(AND(V301="VALID",AF301="Price OK",AG301="Valid Email"),"READY FOR REPORTING","REVIEW REQUIRED") -> READY FOR REPORTING | AI301: =IF(AND(LEFT(A301,LEN(Settings!$B$13))=Settings!$B$13,LEN(A301)=9),"Valid Format","Invalid Format") -> Valid Format | AJ301: =IF(LEFT(C301,LEN(Settings!$B$14))=Settings!$B$14,"Valid Format","Invalid Format") -> Valid Format | AK301: =IF(COUNTIF(Master_Data!$G$5:$G$14,C301)=1,"Known Customer","Customer Not in Master") -> Customer Not in Master | AL301: =IF(U301>=Settings!$B$11,"Target Met","Below Target") -> Below Target | AM301: =IF(YEAR(B301)=Settings!$B$5,"Correct Year","Wrong Year") -> Correct Year | AN301: =COUNTIF(AI301:AM301,"*Valid*")+COUNTIF(AI301:AM301,"Known Customer")+COUNTIF(AI301:AM301,"Target Met")+COUNTIF(AI301:AM301,"Correct Year") -> 3

Sheet Raw_Data
A1: Order_ID | B1: Order_Date | C1: Customer_ID | D1: Customer_Email | E1: Product_ID | F1: Product_Name | G1: Category | H1: Region | I1: Sales_Channel | J1: Sales_Representative | K1: Quantity | L1: Unit_Price | M1: Unit_Cost | N1: Discount_Rate | O1: Payment_Method | P1: Order_Status
A2: ORD-10001 | B2: 45670 | C2: C1029 | D2: client36@example.com | E2: P1002 | F2: Wireless Mouse | G2: Accessories | H2: Bucharest | I2: Marketplace | J2: Ioana Pavel | K2: 12 | L2: 85 | M2: 44 | N2: 0.05 | O2: Card | P2: Completed
A3: ORD-10002 | B3: 45874 | C3: C1028 | D3: client60@example.com | E3: P1010 | F3: Headset | G3: Electronics | H3: West | I3: Marketplace | J3: Andrei Pop | K3: 1 | L3: 195 | M3: 105 | N3: 0 | O3: Bank Transfer | P3: Completed
A4: ORD-10003 | B4: 45872 | C4: C1036 | D4: client2@example.com | E4: P1009 | F4: Webcam | G4: Electronics | H4: North | I4: Marketplace | J4: Mihai Radu | K4: 4 | L4: 230 | M4: 132 | N4: 0.1 | O4: Cash | P4: Returned
A5: ORD-10004 | B5: 45737 | C5: C1012 | D5: client98@example.com | E5: P1005 | F5: 24-inch Monitor | G5: Electronics | H5: Bucharest | I5: Store | J5: Elena Stan | K5: 4 | L5: 720 | M5: 510 | N5: 0.05 | O5: Cash | P5: Completed
A6: ORD-10005 | B6: 45893 | C6: C1011 | D6: client142@example.com | E6: P1001 | F6: Laptop Stand | G6: Accessories | H6: South | I6: Marketplace | J6: Ioana Pavel | K6: 9 | L6: 95 | M6: 52 | N6: 0 | O6: Cash | P6: Completed
A7: ORD-10006 | B7: 45756 | C7: C1085 | D7: client59@example.com | E7: P1010 | F7: Headset | G7: Electronics | H7: South | I7: Online | J7: Maria Ionescu | K7: 12 | L7: 195 | M7: 105 | N7: 0 | O7: Card | P7: Completed
A8: ORD-10007 | B8: 45800 | C8: C1021 | D8: client95@example.com | E8: P1007 | F8: Office Chair | G8: Furniture | H8: South | I8: Online | J8: Elena Stan | K8: 8 | L8: 840 | M8: 590 | N8: 0.2 | O8: Card | P8: Completed
A9: ORD-10008 | B9: 45983 | C9: C1032 | D9: client42@example.com | E9: P1010 | F9: Headset | G9: Electronics | H9: East | I9: Store | J9: Elena Stan | K9: 3 | L9: 195 | M9: 105 | N9: 0.15 | O9: Bank Transfer | P9: Cancelled
A10: ORD-10009 | B10: 45686 | C10: C1052 | D10: client69@example.com | E10: P1006 | F10: 27-inch Monitor | G10: Electronics | H10: Bucharest | I10: Online | J10: Ioana Pavel | K10: 4 | L10: 1090 | M10: 790 | N10: 0 | O10: Cash | P10: Completed
A11: ORD-10010 | B11: 45993 | C11: C1059 | D11: invalid-email | E11: P1004 | F11: USB-C Hub | G11: Accessories | H11: South | I11: Online | J11: Maria Ionescu | K11: 8 | L11: 175 | M11: 98 | N11: 0.1 | O11: Cash | P11: Cancelled
A12: ORD-10011 | B12: 45877 | C12: C1029 | D12: client36@example.com | E12: P1010 | F12: Headset | G12: Electronics | H12: West | I12: Store | J12: Andrei Pop | K12: 10 | L12: 195 | M12: 105 | N12: 0.1 | O12: Card | P12: Completed
A13: ORD-10012 | B13: 45736 | C13: C1055 | D13: client153@example.com | E13: P1002 | F13: Wireless Mouse | G13: Accessories | H13: Bucharest | I13: Store | J13: Mihai Radu | K13: 11 | L13: 85 | M13: 44 | N13: 0 | O13: Online Wallet | P13: Cancelled
... A73: ORD-10072 | B73: 45933 | C73: C1106 | D73: client152@example.com | E73: P1010 | F73: Headset | G73: Electronics | H73: South | I73: Store | J73: Maria Ionescu | K73: 8 | L73: 195 | M73: 105 | N73: 0.1 | O73: Card | P73: Completed
A74: ORD-10073 | B74: 45888 | C74: C1079 | D74: client172@example.com | E74: P1005 | F74: 24-inch Monitor | G74: Electronics | I74: Store | J74: Andrei Pop | K74: 4 | L74: 720 | M74: 510 | N74: 0.1 | O74: Online Wallet | P74: Returned
A75: ORD-10074 | B75: 45751 | C75: C1103 | D75: client67@example.com | E75: P1006 | F75: 27-inch Monitor | G75: Electronics | H75: South | I75: Store | J75: Ioana Pavel | K75: 8 | L75: 1090 | M75: 790 | N75: 0 | O75: Cash | P75: Completed
A76: ORD-10075 | B76: 45663 | C76: C1031 | D76: client105@example.com | E76: P1009 | F76: Webcam | G76: Electronics | H76: East | I76: Marketplace | J76: Maria Ionescu | K76: 9 | L76: 230 | M76: 132 | N76: 0 | O76: Online Wallet | P76: Completed
A77: ORD-10076 | B77: 45887 | C77: C1029 | D77: client104@example.com | E77: P1008 | F77: Standing Desk | G77: Furniture | H77: North | I77: Store | J77: Ioana Pavel | K77: 1 | L77: 1450 | M77: 1030 | N77: 0 | O77: Cash | P77: Completed
A78: ORD-10077 | B78: 45941 | C78: C1096 | D78: client141@example.com | E78: P1008 | F78: Standing Desk | G78: Furniture | H78: South | I78: Store | J78: Mihai Radu | K78: 9 | L78: 1450 | M78: 1030 | N78: 0.05 | O78: Cash | P78: Completed
A79: ORD-10078 | B79: 45786 | C79: C1025 | D79: client81@example.com | E79: P1005 | F79: 24-inch Monitor | G79: Electronics | H79: Bucharest | I79: Marketplace | J79: Ioana Pavel | K79: 4 | L79: 720 | M79: 510 | N79: 0 | O79: Bank Transfer | P79: Cancelled
A80: ORD-10079 | B80: 45768 | C80: C1093 | D80: client151@example.com | E80: P1004 | F80: USB-C Hub | G80: Accessories | H80: West | I80: Marketplace | J80: Elena Stan | K80: 12 | L80: 175 | M80: 98 | N80: 0.1 | O80: Card | P80: Completed
A81: ORD-10080 | B81: 45809 | C81: C1039 | D81: client4@example.com | E81: P1004 | F81: USB-C Hub | G81: Accessories | H81: West | I81: Online | J81: Elena Stan | K81: 4 | L81: 175 | M81: 98 | N81: 0.05 | O81: Card | P81: Completed
A82: ORD-10081 | B82: 45941 | C82: C1082 | D82: client126@example.com | E82: P1001 | F82: Laptop Stand | G82: Accessories | H82: Bucharest | I82: Online | J82: Ioana Pavel | K82: 5 | L82: 95 | M82: 52 | N82: 0.2 | O82: Cash | P82: Completed
A83: ORD-10082 | B83: 45903 | C83: C1124 | D83: client14@example.com | E83: P1008 | F83: Standing Desk | G83: Furniture | H83: South | I83: Store | J83: Andrei Pop | K83: 8 | L83: 1450 | M83: 1030 | N83: 0.05 | O83: Card | P83: Completed
A84: ORD-10083 | B84: 45909 | C84: C1088 | D84: client14@example.com | E84: P1007 | F84: Office Chair | G84: Furniture | H84: North | I84: Online | J84: Ioana Pavel | K84: 2 | L84: 840 | M84: 590 | N84: 0.15 | O84: Cash | P84: Cancelled
A85: ORD-10084 | B85: 45785 | C85: C1078 | D85: client153@example.com | E85: P1002 | F85: Wireless Mouse | G85: Accessories | H85: West | I85: Online | J85: Ioana Pavel | K85: 2 | L85: 85 | M85: 44 | N85: 0.15 | O85: Online Wallet | P85: Completed
A86: ORD-10085 | B86: 45884 | C86: C1040 | D86: client146@example.com | E86: P1008 | F86: Standing Desk | G86: Furniture | H86: West | I86: Online | J86: Ioana Pavel | K86: 5 | L86: 1450 | M86: 1030 | N86: 0.15 | O86: Card | P86: Completed
... A144: ORD-10143 | B144: 45737 | C144: C1087 | D144: client21@example.com | E144: P1001 | F144: Laptop Stand | G144: Accessories | H144: South | I144: Store | J144: Mihai Radu | K144: 3 | L144: 95 | M144: 52 | N144: 0.15 | O144: Online Wallet | P144: Completed
A145: ORD-10144 | B145: 45884 | D145: client132@example.com | E145: P1010 | F145: Headset | G145: Electronics | H145: Bucharest | I145: Store | J145: Mihai Radu | K145: 7 | L145: 195 | M145: 105 | N145: 0.05 | O145: Card | P145: Completed
A146: ORD-10145 | B146: 46005 | C146: C1068 | D146: client171@example.com | E146: P1005 | F146: 24-inch Monitor | G146: Electronics | H146: South | I146: Online | J146: Maria Ionescu | K146: 11 | L146: 720 | M146: 510 | N146: 0.15 | O146: Online Wallet | P146: Completed
A147: ORD-10146 | B147: 45686 | C147: C1122 | D147: client55@example.com | E147: P1010 | F147: Headset | G147: Electronics | H147: North | I147: Store | J147: Elena Stan | K147: 1 | L147: 195 | M147: 105 | N147: 0 | O147: Cash | P147: Completed
A148: ORD-10147 | B148: 45661 | C148: C1023 | D148: client34@example.com | E148: P1002 | F148: Wireless Mouse | G148: Accessories | H148: East | I148: Marketplace | J148: Maria Ionescu | K148: 8 | L148: 85 | M148: 44 | N148: 0.2 | O148: Cash | P148: Completed
A149: ORD-10148 | B149: 45861 | C149: C1003 | D149: client118@example.com | E149: P1002 | F149: Wireless Mouse | G149: Accessories | H149: Bucharest | I149: Store | J149: Ioana Pavel | K149: 12 | L149: 85 | M149: 44 | N149: 0 | O149: Online Wallet | P149: Completed
A150: ORD-10149 | B150: 45865 | C150: C1038 | D150: client30@example.com | E150: P1010 | F150: Headset | G150: Electronics | H150: East | I150: Online | J150: Elena Stan | K150: 12 | L150: 195 | M150: 105 | N150: 0.2 | O150: Bank Transfer | P150: Completed
A151: ORD-10150 | B151: 45893 | C151: C1056 | D151: client28@example.com | E151: P1010 | F151: Headset | G151: Electronics | H151: North | I151: Store | J151: Ioana Pavel | K151: 12 | L151: 195 | M151: 105 | N151: 0.05 | O151: Online Wallet | P151: Completed
A152: ORD-10151 | B152: 45698 | C152: C1044 | D152: client57@example.com | E152: P1009 | F152: Webcam | G152: Electronics | H152: South | I152: Online | J152: Andrei Pop | K152: 7 | L152: 230 | M152: 132 | N152: 0.05 | O152: Card | P152: Cancelled
A153: ORD-10152 | B153: 45919 | C153: C1094 | D153: client166@example.com | E153: P1009 | F153: Webcam | G153: Electronics | H153: North | I153: Online | J153: Andrei Pop | K153: 4 | L153: 230 | M153: 132 | N153: 0.05 | O153: Bank Transfer | P153: Completed
A154: ORD-10153 | B154: 45759 | C154: C1098 | D154: client168@example.com | E154: P1005 | F154: 24-inch Monitor | G154: Electronics | H154: Bucharest | I154: Online | J154: Mihai Radu | K154: 3 | L154: 720 | M154: 510 | N154: 0.15 | O154: Online Wallet | P154: Completed
A155: ORD-10154 | B155: 45954 | C155: C1083 | D155: client163@example.com | E155: P1010 | F155: Headset | G155: Electronics | H155: West | I155: Store | J155: Elena Stan | K155: 8 | L155: 195 | M155: 105 | N155: 0.2 | O155: Bank Transfer | P155: Returned
A156: ORD-10155 | B156: 45692 | C156: C1039 | D156: client71@example.com | E156: P1008 | F156: Standing Desk | G156: Furniture | H156: West | I156: Online | J156: Elena Stan | K156: 8 | L156: 1450 | M156: 1030 | N156: 0.1 | O156: Card | P156: Cancelled
A157: ORD-10156 | B157: 45894 | C157: C1048 | D157: client74@example.com | E157: P1005 | F157: 24-inch Monitor | G157: Electronics | H157: Bucharest | I157: Marketplace | J157: Andrei Pop | K157: 8 | L157: 720 | M157: 510 | N157: 0 | O157: Online Wallet | P157: Completed
... A226: ORD-10225 | B226: 45683 | C226: C1082 | D226: client60@example.com | E226: P1004 | F226: USB-C Hub | G226: Accessories | H226: Bucharest | I226: Online | J226: Mihai Radu | K226: 11 | L226: 175 | M226: 98 | N226: 0.15 | O226: Cash | P226: Completed
A227: ORD-10226 | B227: 45709 | C227: C1124 | D227: client141@example.com | E227: P1008 | G227: Furniture | H227: North | I227: Store | J227: Mihai Radu | K227: 11 | L227: 1450 | M227: 1030 | N227: 0 | O227: Online Wallet | P227: Completed
A228: ORD-10227 | B228: 45805 | C228: C1008 | D228: client23@example.com | E228: P1004 | F228: USB-C Hub | G228: Accessories | H228: West | I228: Online | J228: Ioana Pavel | K228: 6 | L228: 175 | M228: 98 | N228: 0.05 | O228: Card | P228: Cancelled
A229: ORD-10228 | B229: 45871 | C229: C1101 | D229: client127@example.com | E229: P1003 | F229: Mechanical Keyboard | G229: Accessories | H229: North | I229: Marketplace | J229: Elena Stan | K229: 3 | L229: 265 | M229: 155 | N229: 0 | O229: Card | P229: Completed
A230: ORD-10229 | B230: 45810 | C230: C1119 | D230: client86@example.com | E230: P1001 | F230: Laptop Stand | G230: Accessories | H230: South | I230: Store | J230: Ioana Pavel | K230: 10 | L230: 95 | M230: 52 | N230: 0.15 | O230: Online Wallet | P230: Completed
A231: ORD-10230 | B231: 45916 | C231: C1104 | D231: client29@example.com | E231: P1003 | F231: Mechanical Keyboard | G231: Accessories | H231: South | I231: Online | J231: Mihai Radu | K231: 8 | L231: 265 | M231: 155 | N231: 0.05 | O231: Cash | P231: Completed
A232: ORD-10231 | B232: 45665 | C232: C1073 | D232: client173@example.com | E232: P1003 | F232: Mechanical Keyboard | G232: Accessories | H232: North | I232: Online | J232: Ioana Pavel | K232: 12 | L232: 265 | M232: 155 | N232: 0.05 | O232: Online Wallet | P232: Completed
A233: ORD-10232 | B233: 45921 | C233: C1086 | D233: client25@example.com | E233: P1007 | F233: Office Chair | G233: Furniture | H233: North | I233: Online | J233: Mihai Radu | K233: 6 | L233: 840 | M233: 590 | N233: 0 | O233: Cash | P233: Completed
A234: ORD-10233 | B234: 45661 | C234: C1058 | D234: client69@example.com | E234: P1004 | F234: USB-C Hub | G234: Accessories | H234: South | I234: Store | J234: Ioana Pavel | K234: 5 | L234: 175 | M234: 98 | N234: 0.1 | O234: Card | P234: Completed
A235: ORD-10234 | B235: 45992 | C235: C1008 | D235: client171@example.com | E235: P1005 | F235: 24-inch Monitor | G235: Electronics | H235: Bucharest | I235: Store | J235: Elena Stan | K235: 6 | L235: 720 | M235: 510 | N235: 0.2 | O235: Bank Transfer | P235: Completed
A236: ORD-10235 | B236: 46009 | C236: C1089 | D236: client31@example.com | E236: P1007 | F236: Office Chair | G236: Furniture | H236: South | I236: Store | J236: Ioana Pavel | K236: 9 | L236: 840 | M236: 590 | N236: 0.2 | O236: Bank Transfer | P236: Completed
A237: ORD-10236 | B237: 45726 | C237: C1096 | D237: client156@example.com | E237: P1004 | F237: USB-C Hub | G237: Accessories | H237: South | I237: Store | J237: Ioana Pavel | K237: 8 | L237: 175 | M237: 98 | N237: 0 | O237: Online Wallet | P237: Completed
A238: ORD-10237 | B238: 45998 | C238: C1097 | D238: client153@example.com | E238: P1009 | F238: Webcam | G238: Electronics | H238: Bucharest | I238: Marketplace | J238: Mihai Radu | K238: 4 | L238: 230 | M238: 132 | N238: 0 | O238: Cash | P238: Cancelled
A239: ORD-10238 | B239: 45946 | C239: C1116 | D239: client130@example.com | E239: P1002 | F239: Wireless Mouse | G239: Accessories | H239: North | I239: Marketplace | J239: Ioana Pavel | K239: 2 | L239: 85 | M239: 44 | N239: 0 | O239: Bank Transfer | P239: Returned
... A261: ORD-10260 | B261: 45736 | C261: C1049 | D261: client146@example.com | E261: P1005 | F261: 24-inch Monitor | G261: Electronics | H261: North | I261: Store | J261: Ioana Pavel | K261: 4 | L261: 720 | M261: 510 | N261: 0.05 | O261: Cash | P261: Completed
B262: 45908 | C262: C1063 | D262: client118@example.com | E262: P1005 | F262: 24-inch Monitor | G262: Electronics | H262: North | I262: Marketplace | J262: Elena Stan | K262: 12 | L262: 720 | M262: 510 | N262: 0.2 | O262: Bank Transfer | P262: Cancelled
A263: ORD-10262 | B263: 45937 | C263: C1083 | D263: client16@example.com | E263: P1003 | F263: Mechanical Keyboard | G263: Accessories | H263: West | I263: Online | J263: Andrei Pop | K263: 8 | L263: 265 | M263: 155 | N263: 0 | O263: Card | P263: Returned
A264: ORD-10263 | B264: 45869 | C264: C1009 | D264: client39@example.com | E264: P1001 | F264: Laptop Stand | G264: Accessories | H264: Bucharest | I264: Online | J264: Ioana Pavel | K264: 3 | L264: 95 | M264: 52 | N264: 0.2 | O264: Online Wallet | P264: Completed
A265: ORD-10264 | B265: 45688 | C265: C1120 | D265: client158@example.com | E265: P1006 | F265: 27-inch Monitor | G265: Electronics | H265: East | I265: Marketplace | J265: Mihai Radu | K265: 10 | L265: 1090 | M265: 790 | N265: 0.2 | O265: Card | P265: Cancelled
A266: ORD-10265 | B266: 45930 | C266: C1003 | D266: client136@example.com | E266: P1001 | F266: Laptop Stand | G266: Accessories | H266: South | I266: Marketplace | J266: Elena Stan | K266: 9 | L266: 95 | M266: 52 | N266: 0.1 | O266: Card | P266: Completed
A267: ORD-10266 | B267: 46015 | C267: C1014 | D267: client25@example.com | E267: P1009 | F267: Webcam | G267: Electronics | H267: West | I267: Online | J267: Maria Ionescu | K267: 11 | L267: 230 | M267: 132 | N267: 0.1 | O267: Bank Transfer | P267: Completed
A268: ORD-10267 | B268: 45927 | C268: C1102 | D268: client102@example.com | E268: P1010 | F268: Headset | G268: Electronics | H268: Bucharest | I268: Store | J268: Mihai Radu | K268: 5 | L268: 195 | M268: 105 | N268: 0.05 | O268: Online Wallet | P268: Completed
A269: ORD-10268 | B269: 45782 | C269: C1088 | D269: client21@example.com | E269: P1010 | F269: Headset | G269: Electronics | H269: Bucharest | I269: Online | J269: Mihai Radu | K269: 12 | L269: 195 | M269: 105 | N269: 0 | O269: Online Wallet | P269: Completed
A270: ORD-10269 | B270: 45940 | C270: C1002 | D270: client180@example.com | E270: P1007 | F270: Office Chair | G270: Furniture | H270: North | I270: Online | J270: Mihai Radu | K270: 8 | L270: 840 | M270: 590 | N270: 0 | O270: Online Wallet | P270: Cancelled
A271: ORD-10270 | B271: 45947 | C271: C1030 | D271: client55@example.com | E271: P1006 | F271: 27-inch Monitor | G271: Electronics | H271: West | I271: Store | J271: Elena Stan | K271: 2 | L271: 1090 | M271: 790 | N271: 0.15 | O271: Card | P271: Completed
A272: ORD-10271 | B272: 46008 | C272: C1085 | D272: client9@example.com | E272: P1002 | F272: Wireless Mouse | G272: Accessories | H272: North | I272: Store | J272: Andrei Pop | K272: 5 | L272: 85 | M272: 44 | N272: 0.15 | O272: Bank Transfer | P272: Returned
A273: ORD-10272 | B273: 45731 | C273: C1039 | D273: client42@example.com | E273: P1010 | F273: Headset | G273: Electronics | H273: West | I273: Online | J273: Ioana Pavel | K273: 12 | L273: 195 | M273: 105 | N273: 0.1 | O273: Online Wallet | P273: Completed
A274: ORD-10273 | B274: 45827 | C274: C1102 | D274: client177@example.com | E274: P1009 | F274: Webcam | G274: Electronics | H274: Bucharest | I274: Marketplace | J274: Elena Stan | K274: 7 | L274: 230 | M274: 132 | N274: 0.2 | O274: Card | P274: Completed
... A301: ORD-10300 | B301: 45824 | C301: C1034 | D301: client172@example.com | E301: P1006 | F301: 27-inch Monitor | G301: Electronics | H301: East | I301: Marketplace | J301: Elena Stan | K301: 4 | L301: 1090 | M301: 790 | N301: 0.1 | O301: Online Wallet | P301: Completed

Sheet Master_Data
A1: MASTER DATA TABLES
A4: Product_ID | B4: Product_Name | C4: Category | D4: Unit_Price | E4: Unit_Cost | G4: Customer_ID | H4: Customer_Name | I4: Email | J4: Region
A5: P1001 | B5: Laptop Stand | C5: Accessories | D5: 95 | E5: 52 | G5: C1001 | H5: Nova Office | I5: contact@novaoffice.ro | J5: Bucharest
A6: P1002 | B6: Wireless Mouse | C6: Accessories | D6: 85 | E6: 44 | G6: C1002 | H6: Techline SRL | I6: office@techline.ro | J6: North
A7: P1003 | B7: Mechanical Keyboard | C7: Accessories | D7: 265 | E7: 155 | G7: C1003 | H7: Digital Point | I7: sales@digitalpoint.ro | J7: South
A8: P1004 | B8: USB-C Hub | C8: Accessories | D8: 175 | E8: 98 | G8: C1004 | H8: West Retail | I8: contact@westretail.ro | J8: West
A9: P1005 | B9: 24-inch Monitor | C9: Electronics | D9: 720 | E9: 510 | G9: C1005 | H9: East Business | I9: office@eastbusiness.ro | J9: East
A10: P1006 | B10: 27-inch Monitor | C10: Electronics | D10: 1090 | E10: 790 | G10: C1006 | H10: Smart Work | I10: hello@smartwork.ro | J10: Bucharest
A11: P1007 | B11: Office Chair | C11: Furniture | D11: 840 | E11: 590 | G11: C1007 | H11: Office Pro | I11: orders@officepro.ro | J11: North
A12: P1008 | B12: Standing Desk | C12: Furniture | D12: 1450 | E12: 1030 | G12: C1008 | H12: Retail Hub | I12: contact@retailhub.ro | J12: South
A13: P1009 | B13: Webcam | C13: Electronics | D13: 230 | E13: 132 | G13: C1009 | H13: Modern Desk | I13: office@moderndesk.ro | J13: West
A14: P1010 | B14: Headset | C14: Electronics | D14: 195 | E14: 105 | G14: C1010 | H14: Electro Market | I14: sales@electromarket.ro | J14: East
A17: Regions | B17: Sales_Channels | C17: Payment_Methods | D17: Order_Statuses | E17: Sales_Reps | F17: Categories
A18: Bucharest | B18: Online | C18: Card | D18: Completed | E18: Andrei Pop | F18: Accessories
A19: North | B19: Store | C19: Bank Transfer | D19: Returned | E19: Maria Ionescu | F19: Electronics
A20: South | B20: Marketplace | C20: Cash | D20: Cancelled | E20: Elena Stan | F20: Furniture
A21: East | C21: Online Wallet | E21: Mihai Radu
A22: West | E22: Ioana Pavel

Sheet Settings
A1: PROJECT SETTINGS
A4: Setting | B4: Value | C4: Purpose | D4: Used In
A5: Reporting Year | B5: 2025 | C5: Year included in reports | D5: Dashboard and validations
A6: Currency | B6: RON | C6: Display currency | D6: Financial reports
A7: Maximum Discount | B7: 0.5 | C7: Highest approved discount | D7: Clean_Data validation
A8: High Discount Threshold | B8: 0.2 | C8: Flags unusually high discounts | D8: Clean_Data and checklist
A9: Large Order Threshold | B9: 5000 | C9: Classifies large orders | D9: Clean_Data segmentation
A10: Medium Order Threshold | B10: 2000 | C10: Classifies medium orders | D10: Clean_Data segmentation
A11: Target Profit Margin | B11: 0.25 | C11: Desired minimum margin | D11: Checklist and dashboard
A12: Minimum Quantity | B12: 1 | C12: Lowest accepted quantity | D12: Validation
A13: Order ID Prefix | B13: ORD- | C13: Required order ID pattern | D13: Validation
A14: Customer ID Prefix | B14: C | C14: Required customer ID pattern | D14: Validation

Sheet Lookups
A1: Product_ID | B1: Product_Name | C1: Category | D1: Unit_Price | E1: Unit_Cost | G1: Regions | H1: Channels | I1: Sales_Reps | J1: Payment_Methods | K1: Statuses
A2: P1001 | B2: Laptop Stand | C2: Accessories | D2: 95 | E2: 52 | G2: Bucharest | H2: Online | I2: Andrei Pop | J2: Card | K2: Completed
A3: P1002 | B3: Wireless Mouse | C3: Accessories | D3: 85 | E3: 44 | G3: North | H3: Store | I3: Maria Ionescu | J3: Bank Transfer | K3: Returned
A4: P1003 | B4: Mechanical Keyboard | C4: Accessories | D4: 265 | E4: 155 | G4: South | H4: Marketplace | I4: Elena Stan | J4: Cash | K4: Cancelled
A5: P1004 | B5: USB-C Hub | C5: Accessories | D5: 175 | E5: 98 | G5: East | I5: Mihai Radu | J5: Online Wallet
A6: P1005 | B6: 24-inch Monitor | C6: Electronics | D6: 720 | E6: 510 | G6: West | I6: Ioana Pavel
A7: P1006 | B7: 27-inch Monitor | C7: Electronics | D7: 1090 | E7: 790
A8: P1007 | B8: Office Chair | C8: Furniture | D8: 840 | E8: 590
A9: P1008 | B9: Standing Desk | C9: Furniture | D9: 1450 | E9: 1030
A10: P1009 | B10: Webcam | C10: Electronics | D10: 230 | E10: 132
A11: P1010 | B11: Headset | C11: Electronics | D11: 195 | E11: 105

Sheet Data_Validation
A1: DATA QUALITY CONTROL CENTER
A3: Metric | B3: Value | D3: Validation Rule | E3: Field | F3: Expected Condition | G3: Severity | H3: Purpose
A4: Total records | B4: =COUNTA(Clean_Data!A2:A301) -> 300
A5: Valid records | B5: =COUNTIF(Clean_Data!V2:V301,"VALID") -> 291
A6: Records with errors | B6: =COUNTIF(Clean_Data!V2:V301,"ERROR") -> 9
A7: Data quality score | B7: =IFERROR(B5/B4,0) -> 0.97
A8: Duplicate order IDs | B8: =SUMPRODUCT(--(Clean_Data!A2:A301<>""),--(COUNTIF(Clean_Data!A2:A301,Clean_Data!A2:A301)>1)) -> 2
A9: Missing customer IDs | B9: =COUNTBLANK(Clean_Data!C2:C301) -> 0
A10: Invalid emails | B10: =SUMPRODUCT(--(Clean_Data!D2:D301<>""),--ISERROR(SEARCH("@",Clean_Data!D2:D301)))+COUNTBLANK(Clean_Data!D2:D301) -> 1
A11: Unknown products | B11: =SUMPRODUCT(--(COUNTIF(Lookups!A2:A11,Clean_Data!E2:E301)=0)) -> 1
A12: Invalid quantities | B12: =COUNTIF(Clean_Data!K2:K301,"<=0") -> 1
A13: Invalid discounts | B13: =COUNTIF(Clean_Data!N2:N301,">0.5")+COUNTIF(Clean_Data!N2:N301,"<0") -> 1
